[
  {
    "step": 0,
    "type": "origin",
    "name": "Messina, Italy",
    "coords": [
      38.1939,
      15.5552
    ],
    "year": 1103,
    "date_str": "[1103] quies; sine nocte dies, reparatio mira, Vita, dante, tibi pateant ad gaudia vestra. Ipso 84 [68] S.d.- Corbie, S. Pierre. T. Sancti Petri Corbeie. Divitias Bruno mundanasque postposuisti Exemploque tuo postponendas docuisti Et loca deserti pro Rege coluisti, Dulcibus alloquiis multorum corda rigasti, Talibus extemplo factis extas imitator Sanctorum patrum, qui doctrinis viguerunt. Illic insidias hostis per tempora multa Passus mansisti, cujus fraudes superasti. Nunc tamen in Christo complesti fine beato Mortalis vite cursus et gaudia vite Perpetue defunctus habes, hec est tua merces. 85 [71] S.d.- [S. Quentin,] S. Quentin. T: Montis sancti Quintini martyris, Vermandensis pagi. Dum moritur Bruno, moritur; quod traxit ab uno; Stat meritum cujus; quia vivit spiritus ejus. Vita beatorum, spes atque corona piorum, Ipsum sydereis societ super astra choreis.",
    "is_approximate": false,
    "description": "Origin: 20 86 [69] S.d.-Lihons; S. Pierre. T. Sancti Petri..."
  }
]