{
  "roll": {
    "id": 782,
    "roll_num": "105",
    "date_str": "[1103] 115 [77] S.d.- Tournai; cath\u00e9drale (N, VD). T.Sancte Marie Tornacensis. Quem genuisse Colonia, Francia vult aluisse; Gloria Bruno Pater; genti communis utrique; Ascensu facili sociatur ad agmina celi, Quorum civis erat, etiam dum vita manebat. Non tamen hinc frustra comes est oratio justa. Conferat hoc Dominus, meritis quod defuit ejus.",
    "title": "",
    "manuscripts": "",
    "pdf_source": "Dufour T1 (2)",
    "pdf_pages": "86,87",
    "is_verified": 0,
    "year": 1103
  },
  "tituli": [
    {
      "id": 3617,
      "roll_id": 782,
      "title": "Implicit Titulus",
      "location_name": "",
      "latin_text": "5 116 [81] S.d. - Gent, S. Pieters. T. Sancti Petri Blandinensis cenobii. Est commune mori, mors nulli parcit honori. Mors est vita piis, pena diurna malis. Ibimus absque mora, sed qua nescimus in hora, Est quia vita brevis, fluxa, caduca, levis. Ecce, satis scimus, quod non evadere quimus; Et quis erit finis; vermis et inde cinis. Dum vixit, vita nituit satis hic eremita, Mortuus ipse tamen pace quiescat. Amen. 10 15 117 [114] S.d.- [Pr\u00e9aux,] $. L\u00e9ger (1) T. sancti Leodegarii martyris. Poscitis auxilium; prebeat quod Christus in evum. Brunoni petimus migranti corpore Summus; Quatenus optati concedat munera regni. 20 118 [82] S.d.- Gent, S. Baafs. T. Sancti Bavonis in Candavo. In verbis quanquam nobis sit magna facultas;, Non pro posse tamen, sit prodere verba voluntas; Sed flentes breviter dicamus Summe magister; Brunoni charo tibi, Rex, in carne fideli, Cui super omne bonum placuerunt gaudia celi, Illud des esse, quod nusquam novit abesse \" 25 0 (1) Ils'acit Ga",
      "pdf_page": 86,
      "pdf_half": "right",
      "entities": [
        {
          "id": 62879,
          "titulus_id": 3617,
          "original_name": "Gen",
          "original_title": "",
          "footnote_num": "1",
          "footnote_text": "n\" 148 '[115].",
          "normalized_name": "Gen",
          "normalized_role": "n\" 148 '[115].",
          "normalized_dates": "",
          "location_name": ""
        },
        {
          "id": 62880,
          "titulus_id": 3617,
          "original_name": "Pieter",
          "original_title": "",
          "footnote_num": "2",
          "footnote_text": "c [ auDajCUC DcucuicliucaUCLCe",
          "normalized_name": "Pieter",
          "normalized_role": "c [ auDajCUC DcucuicliucaUCLCe",
          "normalized_dates": "",
          "location_name": ""
        },
        {
          "id": 62881,
          "titulus_id": 3617,
          "original_name": "Sancti",
          "original_title": "Blandinensis cenobii",
          "footnote_num": "",
          "footnote_text": "",
          "normalized_name": "Sancti",
          "normalized_role": "Blandinensis cenobii",
          "normalized_dates": "",
          "location_name": ""
        },
        {
          "id": 62882,
          "titulus_id": 3617,
          "original_name": "Blandinensi",
          "original_title": "cenobii",
          "footnote_num": "",
          "footnote_text": "",
          "normalized_name": "Blandinensi",
          "normalized_role": "cenobii",
          "normalized_dates": "",
          "location_name": ""
        },
        {
          "id": 62883,
          "titulus_id": 3617,
          "original_name": "Mors",
          "original_title": "vita piis",
          "footnote_num": "",
          "footnote_text": "",
          "normalized_name": "Mors",
          "normalized_role": "vita piis",
          "normalized_dates": "",
          "location_name": ""
        },
        {
          "id": 62884,
          "titulus_id": 3617,
          "original_name": "Ibimu",
          "original_title": "absque mora",
          "footnote_num": "",
          "footnote_text": "",
          "normalized_name": "Ibimu",
          "normalized_role": "absque mora",
          "normalized_dates": "",
          "location_name": ""
        },
        {
          "id": 62885,
          "titulus_id": 3617,
          "original_name": "Est",
          "original_title": "vita brevis",
          "footnote_num": "",
          "footnote_text": "",
          "normalized_name": "Est",
          "normalized_role": "vita brevis",
          "normalized_dates": "",
          "location_name": ""
        },
        {
          "id": 62886,
          "titulus_id": 3617,
          "original_name": "Ecc",
          "original_title": "",
          "footnote_num": "",
          "footnote_text": "",
          "normalized_name": "Ecc",
          "normalized_role": "",
          "normalized_dates": "",
          "location_name": ""
        },
        {
          "id": 62887,
          "titulus_id": 3617,
          "original_name": "Dum",
          "original_title": "",
          "footnote_num": "",
          "footnote_text": "",
          "normalized_name": "Dum",
          "normalized_role": "",
          "normalized_dates": "",
          "location_name": ""
        },
        {
          "id": 62888,
          "titulus_id": 3617,
          "original_name": "Mortuus",
          "original_title": "tamen pace quiescat",
          "footnote_num": "",
          "footnote_text": "",
          "normalized_name": "Mortuus",
          "normalized_role": "tamen pace quiescat",
          "normalized_dates": "",
          "location_name": ""
        },
        {
          "id": 62889,
          "titulus_id": 3617,
          "original_name": "Ame",
          "original_title": "",
          "footnote_num": "",
          "footnote_text": "",
          "normalized_name": "Ame",
          "normalized_role": "",
          "normalized_dates": "",
          "location_name": ""
        },
        {
          "id": 62890,
          "titulus_id": 3617,
          "original_name": "Pr\u00e9au",
          "original_title": "",
          "footnote_num": "",
          "footnote_text": "",
          "normalized_name": "Pr\u00e9au",
          "normalized_role": "",
          "normalized_dates": "",
          "location_name": ""
        },
        {
          "id": 62891,
          "titulus_id": 3617,
          "original_name": "L\u00e9ger",
          "original_title": ") T",
          "footnote_num": "1",
          "footnote_text": "n\" 148 '[115].",
          "normalized_name": "L\u00e9ger",
          "normalized_role": "n\" 148 '[115].",
          "normalized_dates": "",
          "location_name": ""
        },
        {
          "id": 62892,
          "titulus_id": 3617,
          "original_name": "Leodegari",
          "original_title": "martyris",
          "footnote_num": "",
          "footnote_text": "",
          "normalized_name": "Leodegari",
          "normalized_role": "martyris",
          "normalized_dates": "",
          "location_name": ""
        },
        {
          "id": 62893,
          "titulus_id": 3617,
          "original_name": "Posciti",
          "original_title": "auxilium",
          "footnote_num": "",
          "footnote_text": "",
          "normalized_name": "Posciti",
          "normalized_role": "auxilium",
          "normalized_dates": "",
          "location_name": ""
        },
        {
          "id": 62894,
          "titulus_id": 3617,
          "original_name": "Christus",
          "original_title": "evum",
          "footnote_num": "",
          "footnote_text": "",
          "normalized_name": "Christus",
          "normalized_role": "evum",
          "normalized_dates": "",
          "location_name": ""
        },
        {
          "id": 62895,
          "titulus_id": 3617,
          "original_name": "Brunon",
          "original_title": "petimus migranti corpore Summus",
          "footnote_num": "",
          "footnote_text": "",
          "normalized_name": "Brunon",
          "normalized_role": "petimus migranti corpore Summus",
          "normalized_dates": "",
          "location_name": ""
        },
        {
          "id": 62896,
          "titulus_id": 3617,
          "original_name": "Summu",
          "original_title": "",
          "footnote_num": "",
          "footnote_text": "",
          "normalized_name": "Summu",
          "normalized_role": "",
          "normalized_dates": "",
          "location_name": ""
        },
        {
          "id": 62897,
          "titulus_id": 3617,
          "original_name": "Quatenu",
          "original_title": "optati concedat munera regni",
          "footnote_num": "",
          "footnote_text": "",
          "normalized_name": "Quatenu",
          "normalized_role": "optati concedat munera regni",
          "normalized_dates": "",
          "location_name": ""
        },
        {
          "id": 62898,
          "titulus_id": 3617,
          "original_name": "Gen",
          "original_title": "",
          "footnote_num": "",
          "footnote_text": "",
          "normalized_name": "Gen",
          "normalized_role": "",
          "normalized_dates": "",
          "location_name": ""
        },
        {
          "id": 62899,
          "titulus_id": 3617,
          "original_name": "Baaf",
          "original_title": "",
          "footnote_num": "",
          "footnote_text": "",
          "normalized_name": "Baaf",
          "normalized_role": "",
          "normalized_dates": "",
          "location_name": ""
        },
        {
          "id": 62900,
          "titulus_id": 3617,
          "original_name": "Sanct",
          "original_title": "Bavonis in Candavo",
          "footnote_num": "",
          "footnote_text": "",
          "normalized_name": "Sanct",
          "normalized_role": "Bavonis in Candavo",
          "normalized_dates": "",
          "location_name": ""
        },
        {
          "id": 62901,
          "titulus_id": 3617,
          "original_name": "Bavonis",
          "original_title": "Candavo",
          "footnote_num": "",
          "footnote_text": "",
          "normalized_name": "Bavonis",
          "normalized_role": "Candavo",
          "normalized_dates": "",
          "location_name": ""
        },
        {
          "id": 62902,
          "titulus_id": 3617,
          "original_name": "Candav",
          "original_title": "",
          "footnote_num": "",
          "footnote_text": "",
          "normalized_name": "Candav",
          "normalized_role": "",
          "normalized_dates": "",
          "location_name": ""
        },
        {
          "id": 62903,
          "titulus_id": 3617,
          "original_name": "Non",
          "original_title": "posse tamen",
          "footnote_num": "",
          "footnote_text": "",
          "normalized_name": "Non",
          "normalized_role": "posse tamen",
          "normalized_dates": "",
          "location_name": ""
        },
        {
          "id": 62904,
          "titulus_id": 3617,
          "original_name": "Summ",
          "original_title": "magister",
          "footnote_num": "",
          "footnote_text": "",
          "normalized_name": "Summ",
          "normalized_role": "magister",
          "normalized_dates": "",
          "location_name": ""
        },
        {
          "id": 62905,
          "titulus_id": 3617,
          "original_name": "Brunoni",
          "original_title": "tibi",
          "footnote_num": "",
          "footnote_text": "",
          "normalized_name": "Brunoni",
          "normalized_role": "tibi",
          "normalized_dates": "",
          "location_name": ""
        },
        {
          "id": 62906,
          "titulus_id": 3617,
          "original_name": "Cui",
          "original_title": "omne bonum placuerunt gaudia celi",
          "footnote_num": "",
          "footnote_text": "",
          "normalized_name": "Cui",
          "normalized_role": "omne bonum placuerunt gaudia celi",
          "normalized_dates": "",
          "location_name": ""
        },
        {
          "id": 62907,
          "titulus_id": 3617,
          "original_name": "Illud",
          "original_title": "esse",
          "footnote_num": "",
          "footnote_text": "",
          "normalized_name": "Illud",
          "normalized_role": "esse",
          "normalized_dates": "",
          "location_name": ""
        }
      ]
    },
    {
      "id": 3618,
      "roll_id": 782,
      "title": "Implicit Titulus",
      "location_name": "",
      "latin_text": "ROULEAUX DES MORTS 326 S.d - Coventry; $. Mary 119 '[102] Convatrensis () ecclesie in Anglia. I Sancte Marie Rex Christus in arce polorum Hunc 'pietate sua requie concedat eorum. Gollocet atque frui= 120 [104] S.d.-S. Omer:. I. sancti Audomari episcopi. miseris mortalibus esse solebas; Eteoplen alissistamoquem semper; Bruno; colebas; Ut Pro quo divitias sprevisti totius orbis, 20 U tibi perpetuas daret auctor totius orbis Ergo ~ yera fides; quam tu semper coluisti, Te trahat ad Christi requiem quam, Bruno; petisti. 121 [85] Sd-London; cathedral (S. Paul) . I sancti Pauli apostoli Lundoniensis 15 Tanti fama viri diffusa sub ultima mundi Excitat ardentes in digna precamina mentes; Et licet; ut quimus; complere petita velimus; Vota probatorum passim promissa virorum Nos = pro posse monent; Dominum memorare 20 Brunonem Decessumque sui missis celebrare quotannis. Archidiaconi   Rengerius, Walterus; scholasticus; Theobaldus; Arturus  Quintilianus;   Robertus Durandusque (2) ceterique Lundoniensis;  salutamus omnes canonici ecclesie Sancti Pauli ancie Dengenitrilutamne faternaqub  dilectione impertimus   eremitas Calabrie ecclesie 25 rum fieri singulis annis concedimusque; ut petiistis; anniversa - que   fratribus   cenobii reserendo magistro domino Brunoni, servo Dei, vestri pridie  nonas  octobris   Id cunctis- consensu fratrum ascripsimus in oostrorum ,nomenque ejus toorninibs convessimusospublico memoriam predicte  fratrum 'commemorationis. nostrorum Connatrensis a ; corrigez Convatrensis. Ctte abbaye 1102, de prieur\u00e9 , B\u00e9n\u00e9dictins cath\u00e9dral  devint, Medieral (cf. Knowles/ en 1 1111/1112 religious 'Hadcock, 6 cf: R. W Wales, ) houses: cian in the Hunt, Studies on Pris- p.63). England and dans eleventh   and  twelfth Chanoine  Mediaeval  centuries % de S. Paul , de and London 1941-1943, Renaissance Studies; t.I, de 1086 \u00e0 P 206.",
      "pdf_page": 87,
      "pdf_half": "left",
      "entities": [
        {
          "id": 62908,
          "titulus_id": 3618,
          "original_name": "Coventr",
          "original_title": "",
          "footnote_num": "",
          "footnote_text": "",
          "normalized_name": "Coventr",
          "normalized_role": "",
          "normalized_dates": "",
          "location_name": ""
        },
        {
          "id": 62909,
          "titulus_id": 3618,
          "original_name": "Mary",
          "original_title": "'[102] Convatrensis () ecclesie in Anglia",
          "footnote_num": "",
          "footnote_text": "",
          "normalized_name": "Mary",
          "normalized_role": "'[102] Convatrensis () ecclesie in Anglia",
          "normalized_dates": "",
          "location_name": ""
        },
        {
          "id": 62910,
          "titulus_id": 3618,
          "original_name": "Convatrensi",
          "original_title": "() ecclesie in Anglia",
          "footnote_num": "",
          "footnote_text": "",
          "normalized_name": "Convatrensi",
          "normalized_role": "() ecclesie in Anglia",
          "normalized_dates": "",
          "location_name": ""
        },
        {
          "id": 62911,
          "titulus_id": 3618,
          "original_name": "Angli",
          "original_title": "",
          "footnote_num": "",
          "footnote_text": "",
          "normalized_name": "Angli",
          "normalized_role": "",
          "normalized_dates": "",
          "location_name": ""
        },
        {
          "id": 62912,
          "titulus_id": 3618,
          "original_name": "Sancte",
          "original_title": "Rex Christus in arce polorum Hunc 'pietate sua requie concedat eorum",
          "footnote_num": "",
          "footnote_text": "",
          "normalized_name": "Sancte",
          "normalized_role": "Rex Christus in arce polorum Hunc 'pietate sua requie concedat eorum",
          "normalized_dates": "",
          "location_name": ""
        },
        {
          "id": 62913,
          "titulus_id": 3618,
          "original_name": "Christus",
          "original_title": "arce polorum Hunc 'pietate sua requie concedat eorum",
          "footnote_num": "",
          "footnote_text": "",
          "normalized_name": "Christus",
          "normalized_role": "arce polorum Hunc 'pietate sua requie concedat eorum",
          "normalized_dates": "",
          "location_name": ""
        },
        {
          "id": 62914,
          "titulus_id": 3618,
          "original_name": "Hun",
          "original_title": "'pietate sua requie concedat eorum",
          "footnote_num": "",
          "footnote_text": "",
          "normalized_name": "Hun",
          "normalized_role": "'pietate sua requie concedat eorum",
          "normalized_dates": "",
          "location_name": ""
        },
        {
          "id": 62915,
          "titulus_id": 3618,
          "original_name": "Gollocet",
          "original_title": "frui= 120 [104] S",
          "footnote_num": "",
          "footnote_text": "",
          "normalized_name": "Gollocet",
          "normalized_role": "frui= 120 [104] S",
          "normalized_dates": "",
          "location_name": ""
        },
        {
          "id": 62916,
          "titulus_id": 3618,
          "original_name": "Ome",
          "original_title": ":",
          "footnote_num": "",
          "footnote_text": "",
          "normalized_name": "Ome",
          "normalized_role": ":",
          "normalized_dates": "",
          "location_name": ""
        },
        {
          "id": 62917,
          "titulus_id": 3618,
          "original_name": "Audomar",
          "original_title": "episcopi",
          "footnote_num": "",
          "footnote_text": "",
          "normalized_name": "Audomar",
          "normalized_role": "episcopi",
          "normalized_dates": "",
          "location_name": ""
        },
        {
          "id": 62918,
          "titulus_id": 3618,
          "original_name": "Eteople",
          "original_title": "alissistamoquem semper",
          "footnote_num": "",
          "footnote_text": "",
          "normalized_name": "Eteople",
          "normalized_role": "alissistamoquem semper",
          "normalized_dates": "",
          "location_name": ""
        },
        {
          "id": 62919,
          "titulus_id": 3618,
          "original_name": "Brun",
          "original_title": "",
          "footnote_num": "",
          "footnote_text": "",
          "normalized_name": "Brun",
          "normalized_role": "",
          "normalized_dates": "",
          "location_name": ""
        },
        {
          "id": 62920,
          "titulus_id": 3618,
          "original_name": "Pro",
          "original_title": "divitias sprevisti totius orbis",
          "footnote_num": "",
          "footnote_text": "",
          "normalized_name": "Pro",
          "normalized_role": "divitias sprevisti totius orbis",
          "normalized_dates": "",
          "location_name": ""
        },
        {
          "id": 62921,
          "titulus_id": 3618,
          "original_name": "Erg",
          "original_title": "~ yera fides",
          "footnote_num": "",
          "footnote_text": "",
          "normalized_name": "Erg",
          "normalized_role": "~ yera fides",
          "normalized_dates": "",
          "location_name": ""
        },
        {
          "id": 62922,
          "titulus_id": 3618,
          "original_name": "Christ",
          "original_title": "requiem quam",
          "footnote_num": "",
          "footnote_text": "",
          "normalized_name": "Christ",
          "normalized_role": "requiem quam",
          "normalized_dates": "",
          "location_name": ""
        },
        {
          "id": 62923,
          "titulus_id": 3618,
          "original_name": "Brun",
          "original_title": "",
          "footnote_num": "",
          "footnote_text": "",
          "normalized_name": "Brun",
          "normalized_role": "",
          "normalized_dates": "",
          "location_name": ""
        },
        {
          "id": 62924,
          "titulus_id": 3618,
          "original_name": "Sd-Londo",
          "original_title": "",
          "footnote_num": "",
          "footnote_text": "",
          "normalized_name": "Sd-Londo",
          "normalized_role": "",
          "normalized_dates": "",
          "location_name": ""
        },
        {
          "id": 62925,
          "titulus_id": 3618,
          "original_name": "Pau",
          "original_title": ")",
          "footnote_num": "",
          "footnote_text": "",
          "normalized_name": "Pau",
          "normalized_role": ")",
          "normalized_dates": "",
          "location_name": ""
        },
        {
          "id": 62926,
          "titulus_id": 3618,
          "original_name": "Paul",
          "original_title": "apostoli Lundoniensis 15 Tanti fama viri diffusa sub ultima mundi Excitat ardentes in digna precamina mentes",
          "footnote_num": "",
          "footnote_text": "",
          "normalized_name": "Paul",
          "normalized_role": "apostoli Lundoniensis 15 Tanti fama viri diffusa sub ultima mundi Excitat ardentes in digna precamina mentes",
          "normalized_dates": "",
          "location_name": ""
        },
        {
          "id": 62927,
          "titulus_id": 3618,
          "original_name": "Lundoniensis",
          "original_title": "Tanti fama viri diffusa sub ultima mundi Excitat ardentes in digna precamina mentes",
          "footnote_num": "",
          "footnote_text": "",
          "normalized_name": "Lundoniensis",
          "normalized_role": "Tanti fama viri diffusa sub ultima mundi Excitat ardentes in digna precamina mentes",
          "normalized_dates": "",
          "location_name": ""
        },
        {
          "id": 62928,
          "titulus_id": 3618,
          "original_name": "Tanti",
          "original_title": "viri diffusa sub ultima mundi Excitat ardentes in digna precamina mentes",
          "footnote_num": "",
          "footnote_text": "",
          "normalized_name": "Tanti",
          "normalized_role": "viri diffusa sub ultima mundi Excitat ardentes in digna precamina mentes",
          "normalized_dates": "",
          "location_name": ""
        },
        {
          "id": 62929,
          "titulus_id": 3618,
          "original_name": "Excita",
          "original_title": "ardentes in digna precamina mentes",
          "footnote_num": "",
          "footnote_text": "",
          "normalized_name": "Excita",
          "normalized_role": "ardentes in digna precamina mentes",
          "normalized_dates": "",
          "location_name": ""
        },
        {
          "id": 62930,
          "titulus_id": 3618,
          "original_name": "Vot",
          "original_title": "probatorum passim promissa virorum Nos = pro posse monent",
          "footnote_num": "",
          "footnote_text": "",
          "normalized_name": "Vot",
          "normalized_role": "probatorum passim promissa virorum Nos = pro posse monent",
          "normalized_dates": "",
          "location_name": ""
        },
        {
          "id": 62931,
          "titulus_id": 3618,
          "original_name": "Dominu",
          "original_title": "memorare 20 Brunonem Decessumque sui missis celebrare quotannis",
          "footnote_num": "",
          "footnote_text": "",
          "normalized_name": "Dominu",
          "normalized_role": "memorare 20 Brunonem Decessumque sui missis celebrare quotannis",
          "normalized_dates": "",
          "location_name": ""
        },
        {
          "id": 62932,
          "titulus_id": 3618,
          "original_name": "Brunone",
          "original_title": "Decessumque sui missis celebrare quotannis",
          "footnote_num": "",
          "footnote_text": "",
          "normalized_name": "Brunone",
          "normalized_role": "Decessumque sui missis celebrare quotannis",
          "normalized_dates": "",
          "location_name": ""
        },
        {
          "id": 62933,
          "titulus_id": 3618,
          "original_name": "Decessumque",
          "original_title": "missis celebrare quotannis",
          "footnote_num": "",
          "footnote_text": "",
          "normalized_name": "Decessumque",
          "normalized_role": "missis celebrare quotannis",
          "normalized_dates": "",
          "location_name": ""
        },
        {
          "id": 62934,
          "titulus_id": 3618,
          "original_name": "Archidiacon",
          "original_title": "Rengerius",
          "footnote_num": "",
          "footnote_text": "",
          "normalized_name": "Archidiacon",
          "normalized_role": "Rengerius",
          "normalized_dates": "",
          "location_name": ""
        },
        {
          "id": 62935,
          "titulus_id": 3618,
          "original_name": "Rengeriu",
          "original_title": "",
          "footnote_num": "",
          "footnote_text": "",
          "normalized_name": "Rengeriu",
          "normalized_role": "",
          "normalized_dates": "",
          "location_name": ""
        },
        {
          "id": 62936,
          "titulus_id": 3618,
          "original_name": "Walteru",
          "original_title": "",
          "footnote_num": "",
          "footnote_text": "",
          "normalized_name": "Walteru",
          "normalized_role": "",
          "normalized_dates": "",
          "location_name": ""
        },
        {
          "id": 62937,
          "titulus_id": 3618,
          "original_name": "Theobaldu",
          "original_title": "",
          "footnote_num": "",
          "footnote_text": "",
          "normalized_name": "Theobaldu",
          "normalized_role": "",
          "normalized_dates": "",
          "location_name": ""
        },
        {
          "id": 62938,
          "titulus_id": 3618,
          "original_name": "Arturu",
          "original_title": "Quintilianus",
          "footnote_num": "",
          "footnote_text": "",
          "normalized_name": "Arturu",
          "normalized_role": "Quintilianus",
          "normalized_dates": "",
          "location_name": ""
        },
        {
          "id": 62939,
          "titulus_id": 3618,
          "original_name": "Quintilianu",
          "original_title": "",
          "footnote_num": "",
          "footnote_text": "",
          "normalized_name": "Quintilianu",
          "normalized_role": "",
          "normalized_dates": "",
          "location_name": ""
        },
        {
          "id": 62940,
          "titulus_id": 3618,
          "original_name": "Robertu",
          "original_title": "Durandusque (2) ceterique Lundoniensis",
          "footnote_num": "",
          "footnote_text": "",
          "normalized_name": "Robertu",
          "normalized_role": "Durandusque (2) ceterique Lundoniensis",
          "normalized_dates": "",
          "location_name": ""
        },
        {
          "id": 62941,
          "titulus_id": 3618,
          "original_name": "Durandusque",
          "original_title": ") ceterique Lundoniensis",
          "footnote_num": "2",
          "footnote_text": "c [ auDajCUC DcucuicliucaUCLCe",
          "normalized_name": "Durandusque",
          "normalized_role": "c [ auDajCUC DcucuicliucaUCLCe",
          "normalized_dates": "",
          "location_name": ""
        },
        {
          "id": 62942,
          "titulus_id": 3618,
          "original_name": "Lundoniensi",
          "original_title": "",
          "footnote_num": "",
          "footnote_text": "",
          "normalized_name": "Lundoniensi",
          "normalized_role": "",
          "normalized_dates": "",
          "location_name": ""
        },
        {
          "id": 62943,
          "titulus_id": 3618,
          "original_name": "Sancti",
          "original_title": "ancie Dengenitrilutamne faternaqub  dilectione impertimus   eremitas Calabrie ecclesie 25 rum fieri singulis annis concedimusque",
          "footnote_num": "",
          "footnote_text": "",
          "normalized_name": "Sancti",
          "normalized_role": "ancie Dengenitrilutamne faternaqub  dilectione impertimus   eremitas Calabrie ecclesie 25 rum fieri singulis annis concedimusque",
          "normalized_dates": "",
          "location_name": ""
        },
        {
          "id": 62944,
          "titulus_id": 3618,
          "original_name": "Dengenitrilutamn",
          "original_title": "faternaqub  dilectione impertimus   eremitas Calabrie ecclesie 25 rum fieri singulis annis concedimusque",
          "footnote_num": "",
          "footnote_text": "",
          "normalized_name": "Dengenitrilutamn",
          "normalized_role": "faternaqub  dilectione impertimus   eremitas Calabrie ecclesie 25 rum fieri singulis annis concedimusque",
          "normalized_dates": "",
          "location_name": ""
        },
        {
          "id": 62945,
          "titulus_id": 3618,
          "original_name": "Calabri",
          "original_title": "ecclesie 25 rum fieri singulis annis concedimusque",
          "footnote_num": "",
          "footnote_text": "",
          "normalized_name": "Calabri",
          "normalized_role": "ecclesie 25 rum fieri singulis annis concedimusque",
          "normalized_dates": "",
          "location_name": ""
        },
        {
          "id": 62946,
          "titulus_id": 3618,
          "original_name": "Brunon",
          "original_title": "",
          "footnote_num": "",
          "footnote_text": "",
          "normalized_name": "Brunon",
          "normalized_role": "",
          "normalized_dates": "",
          "location_name": ""
        },
        {
          "id": 62947,
          "titulus_id": 3618,
          "original_name": "Connatrensis",
          "original_title": "",
          "footnote_num": "",
          "footnote_text": "",
          "normalized_name": "Connatrensis",
          "normalized_role": "",
          "normalized_dates": "",
          "location_name": ""
        },
        {
          "id": 62948,
          "titulus_id": 3618,
          "original_name": "Convatrensi",
          "original_title": "",
          "footnote_num": "",
          "footnote_text": "",
          "normalized_name": "Convatrensi",
          "normalized_role": "",
          "normalized_dates": "",
          "location_name": ""
        },
        {
          "id": 62949,
          "titulus_id": 3618,
          "original_name": "Ctt",
          "original_title": "abbaye 1102",
          "footnote_num": "",
          "footnote_text": "",
          "normalized_name": "Ctt",
          "normalized_role": "abbaye 1102",
          "normalized_dates": "",
          "location_name": ""
        },
        {
          "id": 62950,
          "titulus_id": 3618,
          "original_name": "B\u00e9n\u00e9dictin",
          "original_title": "cath\u00e9dral  devint",
          "footnote_num": "",
          "footnote_text": "",
          "normalized_name": "B\u00e9n\u00e9dictin",
          "normalized_role": "cath\u00e9dral  devint",
          "normalized_dates": "",
          "location_name": ""
        },
        {
          "id": 62951,
          "titulus_id": 3618,
          "original_name": "Medieral",
          "original_title": "",
          "footnote_num": "",
          "footnote_text": "",
          "normalized_name": "Medieral",
          "normalized_role": "",
          "normalized_dates": "",
          "location_name": ""
        },
        {
          "id": 62952,
          "titulus_id": 3618,
          "original_name": "Knowle",
          "original_title": "/ en 1 1111/1112 religious 'Hadcock",
          "footnote_num": "",
          "footnote_text": "",
          "normalized_name": "Knowle",
          "normalized_role": "/ en 1 1111/1112 religious 'Hadcock",
          "normalized_dates": "",
          "location_name": ""
        },
        {
          "id": 62953,
          "titulus_id": 3618,
          "original_name": "Hadcoc",
          "original_title": "",
          "footnote_num": "",
          "footnote_text": "",
          "normalized_name": "Hadcoc",
          "normalized_role": "",
          "normalized_dates": "",
          "location_name": ""
        },
        {
          "id": 62954,
          "titulus_id": 3618,
          "original_name": "Wale",
          "original_title": "",
          "footnote_num": "",
          "footnote_text": "",
          "normalized_name": "Wale",
          "normalized_role": "",
          "normalized_dates": "",
          "location_name": ""
        },
        {
          "id": 62955,
          "titulus_id": 3618,
          "original_name": "Hun",
          "original_title": "",
          "footnote_num": "",
          "footnote_text": "",
          "normalized_name": "Hun",
          "normalized_role": "",
          "normalized_dates": "",
          "location_name": ""
        },
        {
          "id": 62956,
          "titulus_id": 3618,
          "original_name": "Studies",
          "original_title": "Pris- p",
          "footnote_num": "",
          "footnote_text": "",
          "normalized_name": "Studies",
          "normalized_role": "Pris- p",
          "normalized_dates": "",
          "location_name": ""
        },
        {
          "id": 62957,
          "titulus_id": 3618,
          "original_name": "Pris-",
          "original_title": "",
          "footnote_num": "",
          "footnote_text": "",
          "normalized_name": "Pris-",
          "normalized_role": "",
          "normalized_dates": "",
          "location_name": ""
        },
        {
          "id": 62958,
          "titulus_id": 3618,
          "original_name": "England",
          "original_title": "dans eleventh   and  twelfth Chanoine  Mediaeval  centuries % de S",
          "footnote_num": "",
          "footnote_text": "",
          "normalized_name": "England",
          "normalized_role": "dans eleventh   and  twelfth Chanoine  Mediaeval  centuries % de S",
          "normalized_dates": "",
          "location_name": ""
        },
        {
          "id": 62959,
          "titulus_id": 3618,
          "original_name": "Chanoin",
          "original_title": "Mediaeval  centuries % de S",
          "footnote_num": "",
          "footnote_text": "",
          "normalized_name": "Chanoin",
          "normalized_role": "Mediaeval  centuries % de S",
          "normalized_dates": "",
          "location_name": ""
        },
        {
          "id": 62960,
          "titulus_id": 3618,
          "original_name": "Mediaeva",
          "original_title": "centuries % de S",
          "footnote_num": "",
          "footnote_text": "",
          "normalized_name": "Mediaeva",
          "normalized_role": "centuries % de S",
          "normalized_dates": "",
          "location_name": ""
        },
        {
          "id": 62961,
          "titulus_id": 3618,
          "original_name": "Pau",
          "original_title": "",
          "footnote_num": "",
          "footnote_text": "",
          "normalized_name": "Pau",
          "normalized_role": "",
          "normalized_dates": "",
          "location_name": ""
        },
        {
          "id": 62962,
          "titulus_id": 3618,
          "original_name": "London",
          "original_title": "-1943",
          "footnote_num": "",
          "footnote_text": "",
          "normalized_name": "London",
          "normalized_role": "-1943",
          "normalized_dates": "",
          "location_name": ""
        },
        {
          "id": 62963,
          "titulus_id": 3618,
          "original_name": "Renaissanc",
          "original_title": "Studies",
          "footnote_num": "",
          "footnote_text": "",
          "normalized_name": "Renaissanc",
          "normalized_role": "Studies",
          "normalized_dates": "",
          "location_name": ""
        },
        {
          "id": 62964,
          "titulus_id": 3618,
          "original_name": "Studie",
          "original_title": "",
          "footnote_num": "",
          "footnote_text": "",
          "normalized_name": "Studie",
          "normalized_role": "",
          "normalized_dates": "",
          "location_name": ""
        }
      ]
    }
  ],
  "footnotes": [
    {
      "id": 3600,
      "roll_id": 782,
      "pdf_page": 86,
      "pdf_half": "right",
      "footnote_num": "1",
      "text": "n\" 148 '[115]."
    },
    {
      "id": 3601,
      "roll_id": 782,
      "pdf_page": 86,
      "pdf_half": "right",
      "footnote_num": "2",
      "text": "c [ auDajCUC DcucuicliucaUCLCe"
    }
  ]
}