[
  {
    "step": 0,
    "type": "origin",
    "name": "Rouleau",
    "coords": null,
    "year": 1016,
    "date_str": "1016, novembre 1047, juin",
    "description": "Origin: Rouleau d'Oliba; abb\u00e9 de Ripoll et de $ Michel de ..."
  },
  {
    "step": 1,
    "type": "stop",
    "name": "Fleury Abbey, France",
    "coords": [
      47.8093,
      2.3053
    ],
    "year": 971,
    "date_str": "971 [?]-1046",
    "description": "Visited: Caserrass (Pul Oliva)"
  },
  {
    "step": 2,
    "type": "stop",
    "name": "par",
    "coords": null,
    "year": 971,
    "date_str": "971 [?]-1046",
    "description": "Visited: Marti (Callia Juagiu P de christiana)"
  },
  {
    "step": 3,
    "type": "stop",
    "name": "Limoges",
    "coords": null,
    "year": 971,
    "date_str": "971 [?]-1046",
    "description": "Visited: Martin (1 Gereslees)"
  },
  {
    "step": 4,
    "type": "stop",
    "name": "Fleury Abbey, France",
    "coords": [
      47.8093,
      2.3053
    ],
    "year": 971,
    "date_str": "971 [?]-1046",
    "description": "Visited: Lemovicens (Pul Oliva)"
  },
  {
    "step": 5,
    "type": "stop",
    "name": "par",
    "coords": null,
    "year": 971,
    "date_str": "971 [?]-1046",
    "description": "Visited: Martinus (Callia Juagiu P de christiana)"
  },
  {
    "step": 6,
    "type": "stop",
    "name": "Limoges",
    "coords": null,
    "year": 971,
    "date_str": "971 [?]-1046",
    "description": "Visited: Christo (1 Gereslees)"
  },
  {
    "step": 7,
    "type": "stop",
    "name": "Fleury Abbey, France",
    "coords": [
      47.8093,
      2.3053
    ],
    "year": 971,
    "date_str": "971 [?]-1046",
    "description": "Visited: Pictavis (Pul Oliva)"
  },
  {
    "step": 8,
    "type": "stop",
    "name": "par",
    "coords": null,
    "year": 971,
    "date_str": "971 [?]-1046",
    "description": "Visited: Marti (Callia Juagiu P de christiana)"
  },
  {
    "step": 9,
    "type": "stop",
    "name": "Limoges",
    "coords": null,
    "year": 971,
    "date_str": "971 [?]-1046",
    "description": "Visited: Martin (1 Gereslees)"
  },
  {
    "step": 10,
    "type": "stop",
    "name": "Fleury Abbey, France",
    "coords": [
      47.8093,
      2.3053
    ],
    "year": 971,
    "date_str": "971 [?]-1046",
    "description": "Visited: Nos (Pul Oliva)"
  },
  {
    "step": 11,
    "type": "stop",
    "name": "par",
    "coords": null,
    "year": 971,
    "date_str": "971 [?]-1046",
    "description": "Visited: Lorenzo (Callia Juagiu P de christiana)"
  },
  {
    "step": 12,
    "type": "stop",
    "name": "Limoges",
    "coords": null,
    "year": 971,
    "date_str": "971 [?]-1046",
    "description": "Visited: Bevite (1 Gereslees)"
  },
  {
    "step": 13,
    "type": "stop",
    "name": "Fleury Abbey, France",
    "coords": [
      47.8093,
      2.3053
    ],
    "year": 971,
    "date_str": "971 [?]-1046",
    "description": "Visited: Pos (Pul Oliva)"
  },
  {
    "step": 14,
    "type": "stop",
    "name": "par",
    "coords": null,
    "year": 971,
    "date_str": "971 [?]-1046",
    "description": "Visited: Nos (Callia Juagiu P de christiana)"
  },
  {
    "step": 15,
    "type": "stop",
    "name": "Limoges",
    "coords": null,
    "year": 971,
    "date_str": "971 [?]-1046",
    "description": "Visited: Itaque (1 Gereslees)"
  },
  {
    "step": 16,
    "type": "stop",
    "name": "Fleury Abbey, France",
    "coords": [
      47.8093,
      2.3053
    ],
    "year": 971,
    "date_str": "971 [?]-1046",
    "description": "Visited: Ermenisclus (Pul Oliva)"
  },
  {
    "step": 17,
    "type": "stop",
    "name": "par",
    "coords": null,
    "year": 971,
    "date_str": "971 [?]-1046",
    "description": "Visited: Dominum (Callia Juagiu P de christiana)"
  },
  {
    "step": 18,
    "type": "stop",
    "name": "Limoges",
    "coords": null,
    "year": 971,
    "date_str": "971 [?]-1046",
    "description": "Visited: Quod (1 Gereslees)"
  },
  {
    "step": 19,
    "type": "stop",
    "name": "Fleury Abbey, France",
    "coords": [
      47.8093,
      2.3053
    ],
    "year": 971,
    "date_str": "971 [?]-1046",
    "description": "Visited: Quis (Pul Oliva)"
  },
  {
    "step": 20,
    "type": "stop",
    "name": "par",
    "coords": null,
    "year": 971,
    "date_str": "971 [?]-1046",
    "description": "Visited: Serratei (Callia Juagiu P de christiana)"
  },
  {
    "step": 21,
    "type": "stop",
    "name": "Limoges",
    "coords": null,
    "year": 971,
    "date_str": "971 [?]-1046",
    "description": "Visited: Rivipoh (1 Gereslees)"
  },
  {
    "step": 22,
    "type": "stop",
    "name": "Fleury Abbey, France",
    "coords": [
      47.8093,
      2.3053
    ],
    "year": 971,
    "date_str": "971 [?]-1046",
    "description": "Visited: Pro (Pul Oliva)"
  },
  {
    "step": 23,
    "type": "stop",
    "name": "par",
    "coords": null,
    "year": 971,
    "date_str": "971 [?]-1046",
    "description": "Visited: Ghrignornfisatribus (Callia Juagiu P de christiana)"
  },
  {
    "step": 24,
    "type": "stop",
    "name": "Limoges",
    "coords": null,
    "year": 971,
    "date_str": "971 [?]-1046",
    "description": "Visited: Christoguarissimis (1 Gereslees)"
  },
  {
    "step": 25,
    "type": "stop",
    "name": "Fleury Abbey, France",
    "coords": [
      47.8093,
      2.3053
    ],
    "year": 971,
    "date_str": "971 [?]-1046",
    "description": "Visited: Illacrimaveruntque (Pul Oliva)"
  },
  {
    "step": 26,
    "type": "stop",
    "name": "par",
    "coords": null,
    "year": 971,
    "date_str": "971 [?]-1046",
    "description": "Visited: Suyas (Callia Juagiu P de christiana)"
  },
  {
    "step": 27,
    "type": "stop",
    "name": "Limoges",
    "coords": null,
    "year": 971,
    "date_str": "971 [?]-1046",
    "description": "Visited: En (1 Gereslees)"
  },
  {
    "step": 28,
    "type": "stop",
    "name": "Fleury Abbey, France",
    "coords": [
      47.8093,
      2.3053
    ],
    "year": 971,
    "date_str": "971 [?]-1046",
    "description": "Visited: Camprodo (Pul Oliva)"
  },
  {
    "step": 29,
    "type": "stop",
    "name": "par",
    "coords": null,
    "year": 971,
    "date_str": "971 [?]-1046",
    "description": "Visited: No (Callia Juagiu P de christiana)"
  },
  {
    "step": 30,
    "type": "stop",
    "name": "Limoges",
    "coords": null,
    "year": 971,
    "date_str": "971 [?]-1046",
    "description": "Visited: Monasterio (1 Gereslees)"
  },
  {
    "step": 31,
    "type": "stop",
    "name": "Fleury Abbey, France",
    "coords": [
      47.8093,
      2.3053
    ],
    "year": 971,
    "date_str": "971 [?]-1046",
    "description": "Visited: Olibe (Pul Oliva)"
  },
  {
    "step": 32,
    "type": "stop",
    "name": "par",
    "coords": null,
    "year": 971,
    "date_str": "971 [?]-1046",
    "description": "Visited: El (Callia Juagiu P de christiana)"
  },
  {
    "step": 33,
    "type": "stop",
    "name": "Limoges",
    "coords": null,
    "year": 971,
    "date_str": "971 [?]-1046",
    "description": "Visited: Cana (1 Gereslees)"
  },
  {
    "step": 34,
    "type": "stop",
    "name": "Fleury Abbey, France",
    "coords": [
      47.8093,
      2.3053
    ],
    "year": 971,
    "date_str": "971 [?]-1046",
    "description": "Visited: Paris (Pul Oliva)"
  },
  {
    "step": 35,
    "type": "stop",
    "name": "par",
    "coords": null,
    "year": 971,
    "date_str": "971 [?]-1046",
    "description": "Visited: Olim (Callia Juagiu P de christiana)"
  },
  {
    "step": 36,
    "type": "stop",
    "name": "Limoges",
    "coords": null,
    "year": 971,
    "date_str": "971 [?]-1046",
    "description": "Visited: Dum (1 Gereslees)"
  },
  {
    "step": 37,
    "type": "stop",
    "name": "Fleury Abbey, France",
    "coords": [
      47.8093,
      2.3053
    ],
    "year": 971,
    "date_str": "971 [?]-1046",
    "description": "Visited: Flebilibus (Pul Oliva)"
  },
  {
    "step": 38,
    "type": "stop",
    "name": "par",
    "coords": null,
    "year": 971,
    "date_str": "971 [?]-1046",
    "description": "Visited: Iemporis (Callia Juagiu P de christiana)"
  },
  {
    "step": 39,
    "type": "stop",
    "name": "Limoges",
    "coords": null,
    "year": 971,
    "date_str": "971 [?]-1046",
    "description": "Visited: Haec (1 Gereslees)"
  },
  {
    "step": 40,
    "type": "stop",
    "name": "Fleury Abbey, France",
    "coords": [
      47.8093,
      2.3053
    ],
    "year": 971,
    "date_str": "971 [?]-1046",
    "description": "Visited: Col (Pul Oliva)"
  },
  {
    "step": 41,
    "type": "stop",
    "name": "par",
    "coords": null,
    "year": 971,
    "date_str": "971 [?]-1046",
    "description": "Visited: Pujade (Callia Juagiu P de christiana)"
  },
  {
    "step": 42,
    "type": "stop",
    "name": "Limoges",
    "coords": null,
    "year": 971,
    "date_str": "971 [?]-1046",
    "description": "Visited: Cronica (1 Gereslees)"
  },
  {
    "step": 43,
    "type": "stop",
    "name": "Fleury Abbey, France",
    "coords": [
      47.8093,
      2.3053
    ],
    "year": 971,
    "date_str": "971 [?]-1046",
    "description": "Visited: Guisla (Pul Oliva)"
  },
  {
    "step": 44,
    "type": "stop",
    "name": "par",
    "coords": null,
    "year": 971,
    "date_str": "971 [?]-1046",
    "description": "Visited: Ge (Callia Juagiu P de christiana)"
  },
  {
    "step": 45,
    "type": "stop",
    "name": "Limoges",
    "coords": null,
    "year": 971,
    "date_str": "971 [?]-1046",
    "description": "Visited: Il (1 Gereslees)"
  },
  {
    "step": 46,
    "type": "stop",
    "name": "Fleury Abbey, France",
    "coords": [
      47.8093,
      2.3053
    ],
    "year": 971,
    "date_str": "971 [?]-1046",
    "description": "Visited: Catalogn (Pul Oliva)"
  },
  {
    "step": 47,
    "type": "stop",
    "name": "par",
    "coords": null,
    "year": 971,
    "date_str": "971 [?]-1046",
    "description": "Visited: Les (Callia Juagiu P de christiana)"
  },
  {
    "step": 48,
    "type": "stop",
    "name": "Limoges",
    "coords": null,
    "year": 971,
    "date_str": "971 [?]-1046",
    "description": "Visited: Seules (1 Gereslees)"
  },
  {
    "step": 49,
    "type": "stop",
    "name": "Fleury Abbey, France",
    "coords": [
      47.8093,
      2.3053
    ],
    "year": 971,
    "date_str": "971 [?]-1046",
    "description": "Visited: La (Pul Oliva)"
  },
  {
    "step": 50,
    "type": "stop",
    "name": "Limoges",
    "coords": null,
    "year": 971,
    "date_str": "971 [?]-1046",
    "description": "Visited: Notons (1 Gereslees)"
  },
  {
    "step": 51,
    "type": "stop",
    "name": "Fleury Abbey, France",
    "coords": [
      47.8093,
      2.3053
    ],
    "year": 971,
    "date_str": "971 [?]-1046",
    "description": "Visited: Don (Pul Oliva)"
  },
  {
    "step": 52,
    "type": "stop",
    "name": "par",
    "coords": null,
    "year": 971,
    "date_str": "971 [?]-1046",
    "description": "Visited: Seniofredus (Callia Juagiu P de christiana)"
  },
  {
    "step": 53,
    "type": "stop",
    "name": "Limoges",
    "coords": null,
    "year": 971,
    "date_str": "971 [?]-1046",
    "description": "Visited: Renardu (1 Gereslees)"
  },
  {
    "step": 54,
    "type": "stop",
    "name": "Fleury Abbey, France",
    "coords": [
      47.8093,
      2.3053
    ],
    "year": 971,
    "date_str": "971 [?]-1046",
    "description": "Visited: Isi (Pul Oliva)"
  },
  {
    "step": 55,
    "type": "stop",
    "name": "par",
    "coords": null,
    "year": 971,
    "date_str": "971 [?]-1046",
    "description": "Visited: Petrus (Callia Juagiu P de christiana)"
  },
  {
    "step": 56,
    "type": "stop",
    "name": "Limoges",
    "coords": null,
    "year": 971,
    "date_str": "971 [?]-1046",
    "description": "Visited: Petrus (1 Gereslees)"
  },
  {
    "step": 57,
    "type": "stop",
    "name": "Fleury Abbey, France",
    "coords": [
      47.8093,
      2.3053
    ],
    "year": 971,
    "date_str": "971 [?]-1046",
    "description": "Visited: Jetitiam (Pul Oliva)"
  },
  {
    "step": 58,
    "type": "stop",
    "name": "par",
    "coords": null,
    "year": 971,
    "date_str": "971 [?]-1046",
    "description": "Visited: Arulensi (Callia Juagiu P de christiana)"
  },
  {
    "step": 59,
    "type": "stop",
    "name": "Limoges",
    "coords": null,
    "year": 971,
    "date_str": "971 [?]-1046",
    "description": "Visited: Id (1 Gereslees)"
  },
  {
    "step": 60,
    "type": "stop",
    "name": "Fleury Abbey, France",
    "coords": [
      47.8093,
      2.3053
    ],
    "year": 971,
    "date_str": "971 [?]-1046",
    "description": "Visited: Kerulue (Pul Oliva)"
  },
  {
    "step": 61,
    "type": "stop",
    "name": "par",
    "coords": null,
    "year": 971,
    "date_str": "971 [?]-1046",
    "description": "Visited: Christus (Callia Juagiu P de christiana)"
  },
  {
    "step": 62,
    "type": "stop",
    "name": "Limoges",
    "coords": null,
    "year": 971,
    "date_str": "971 [?]-1046",
    "description": "Visited: Jean- (1 Gereslees)"
  },
  {
    "step": 63,
    "type": "stop",
    "name": "Fleury Abbey, France",
    "coords": [
      47.8093,
      2.3053
    ],
    "year": 971,
    "date_str": "971 [?]-1046",
    "description": "Visited: Domin (Pul Oliva)"
  },
  {
    "step": 64,
    "type": "stop",
    "name": "par",
    "coords": null,
    "year": 971,
    "date_str": "971 [?]-1046",
    "description": "Visited: Johanne (Callia Juagiu P de christiana)"
  },
  {
    "step": 65,
    "type": "stop",
    "name": "Limoges",
    "coords": null,
    "year": 971,
    "date_str": "971 [?]-1046",
    "description": "Visited: Valet (1 Gereslees)"
  },
  {
    "step": 66,
    "type": "stop",
    "name": "par",
    "coords": null,
    "year": 1016,
    "date_str": "1016, novembre 1047, juin",
    "description": "Visited: Hon (Callia Juagiu P de christiana)"
  },
  {
    "step": 67,
    "type": "stop",
    "name": "Limoges",
    "coords": null,
    "year": 1016,
    "date_str": "1016, novembre 1047, juin",
    "description": "Visited: Manoguisi (1 Gereslees)"
  },
  {
    "step": 68,
    "type": "stop",
    "name": "Fleury Abbey, France",
    "coords": [
      47.8093,
      2.3053
    ],
    "year": 971,
    "date_str": "971 [?]-1046",
    "description": "Visited: Giscafre- (Pul Oliva)"
  },
  {
    "step": 69,
    "type": "stop",
    "name": "par",
    "coords": null,
    "year": 971,
    "date_str": "971 [?]-1046",
    "description": "Visited: Wannalgaudus (Callia Juagiu P de christiana)"
  },
  {
    "step": 70,
    "type": "stop",
    "name": "Limoges",
    "coords": null,
    "year": 971,
    "date_str": "971 [?]-1046",
    "description": "Visited: Nos (1 Gereslees)"
  },
  {
    "step": 71,
    "type": "stop",
    "name": "Fleury Abbey, France",
    "coords": [
      47.8093,
      2.3053
    ],
    "year": 971,
    "date_str": "971 [?]-1046",
    "description": "Visited: Nomina (Pul Oliva)"
  },
  {
    "step": 72,
    "type": "stop",
    "name": "par",
    "coords": null,
    "year": 971,
    "date_str": "971 [?]-1046",
    "description": "Visited: Bernardo (Callia Juagiu P de christiana)"
  },
  {
    "step": 73,
    "type": "stop",
    "name": "Limoges",
    "coords": null,
    "year": 971,
    "date_str": "971 [?]-1046",
    "description": "Visited: Dapr (1 Gereslees)"
  },
  {
    "step": 74,
    "type": "stop",
    "name": "Fleury Abbey, France",
    "coords": [
      47.8093,
      2.3053
    ],
    "year": 971,
    "date_str": "971 [?]-1046",
    "description": "Visited: Banyole (Pul Oliva)"
  },
  {
    "step": 75,
    "type": "stop",
    "name": "par",
    "coords": null,
    "year": 971,
    "date_str": "971 [?]-1046",
    "description": "Visited: Pro (Callia Juagiu P de christiana)"
  },
  {
    "step": 76,
    "type": "stop",
    "name": "Limoges",
    "coords": null,
    "year": 971,
    "date_str": "971 [?]-1046",
    "description": "Visited: Domini (1 Gereslees)"
  },
  {
    "step": 77,
    "type": "stop",
    "name": "Fleury Abbey, France",
    "coords": [
      47.8093,
      2.3053
    ],
    "year": 971,
    "date_str": "971 [?]-1046",
    "description": "Visited: Obsequiis (Pul Oliva)"
  },
  {
    "step": 78,
    "type": "stop",
    "name": "par",
    "coords": null,
    "year": 971,
    "date_str": "971 [?]-1046",
    "description": "Visited: Gifredi (Callia Juagiu P de christiana)"
  },
  {
    "step": 79,
    "type": "stop",
    "name": "Limoges",
    "coords": null,
    "year": 971,
    "date_str": "971 [?]-1046",
    "description": "Visited: Gualterio (1 Gereslees)"
  },
  {
    "step": 80,
    "type": "stop",
    "name": "Fleury Abbey, France",
    "coords": [
      47.8093,
      2.3053
    ],
    "year": 971,
    "date_str": "971 [?]-1046",
    "description": "Visited: Christi (Pul Oliva)"
  },
  {
    "step": 81,
    "type": "stop",
    "name": "par",
    "coords": null,
    "year": 971,
    "date_str": "971 [?]-1046",
    "description": "Visited: Quidquid (Callia Juagiu P de christiana)"
  },
  {
    "step": 82,
    "type": "stop",
    "name": "Limoges",
    "coords": null,
    "year": 971,
    "date_str": "971 [?]-1046",
    "description": "Visited: Deitati (1 Gereslees)"
  },
  {
    "step": 83,
    "type": "stop",
    "name": "Nanteuil-en-Vall\u00e9e Abbey, France",
    "coords": [
      46.0022,
      0.2818
    ],
    "year": 971,
    "date_str": "971 [?]-1046",
    "description": "Visited: Quod (abb\u00e9 de S. 988)"
  },
  {
    "step": 84,
    "type": "stop",
    "name": "Fleury Abbey, France",
    "coords": [
      47.8093,
      2.3053
    ],
    "year": 971,
    "date_str": "971 [?]-1046",
    "description": "Visited: Bernardus (Pul Oliva)"
  },
  {
    "step": 85,
    "type": "stop",
    "name": "par",
    "coords": null,
    "year": 971,
    "date_str": "971 [?]-1046",
    "description": "Visited: Fotrus (Callia Juagiu P de christiana)"
  },
  {
    "step": 86,
    "type": "stop",
    "name": "Limoges",
    "coords": null,
    "year": 971,
    "date_str": "971 [?]-1046",
    "description": "Visited: Iotuchus (1 Gereslees)"
  },
  {
    "step": 87,
    "type": "stop",
    "name": "Nanteuil-en-Vall\u00e9e Abbey, France",
    "coords": [
      46.0022,
      0.2818
    ],
    "year": 971,
    "date_str": "971 [?]-1046",
    "description": "Visited: Per (abb\u00e9 de S. 988)"
  },
  {
    "step": 88,
    "type": "stop",
    "name": "Fleury Abbey, France",
    "coords": [
      47.8093,
      2.3053
    ],
    "year": 971,
    "date_str": "971 [?]-1046",
    "description": "Visited: Adalbertus (Pul Oliva)"
  },
  {
    "step": 89,
    "type": "stop",
    "name": "par",
    "coords": null,
    "year": 971,
    "date_str": "971 [?]-1046",
    "description": "Visited: Primu (Callia Juagiu P de christiana)"
  },
  {
    "step": 90,
    "type": "stop",
    "name": "Limoges",
    "coords": null,
    "year": 971,
    "date_str": "971 [?]-1046",
    "description": "Visited: Christi (1 Gereslees)"
  },
  {
    "step": 91,
    "type": "stop",
    "name": "Nanteuil-en-Vall\u00e9e Abbey, France",
    "coords": [
      46.0022,
      0.2818
    ],
    "year": 971,
    "date_str": "971 [?]-1046",
    "description": "Visited: Qu (abb\u00e9 de S. 988)"
  },
  {
    "step": 92,
    "type": "stop",
    "name": "Fleury Abbey, France",
    "coords": [
      47.8093,
      2.3053
    ],
    "year": 971,
    "date_str": "971 [?]-1046",
    "description": "Visited: Petrus (Pul Oliva)"
  },
  {
    "step": 93,
    "type": "stop",
    "name": "par",
    "coords": null,
    "year": 971,
    "date_str": "971 [?]-1046",
    "description": "Visited: Il (Callia Juagiu P de christiana)"
  },
  {
    "step": 94,
    "type": "stop",
    "name": "Limoges",
    "coords": null,
    "year": 971,
    "date_str": "971 [?]-1046",
    "description": "Visited: Recuci (1 Gereslees)"
  },
  {
    "step": 95,
    "type": "stop",
    "name": "Nanteuil-en-Vall\u00e9e Abbey, France",
    "coords": [
      46.0022,
      0.2818
    ],
    "year": 971,
    "date_str": "971 [?]-1046",
    "description": "Visited: Barcclona (abb\u00e9 de S. 988)"
  },
  {
    "step": 96,
    "type": "stop",
    "name": "Fleury Abbey, France",
    "coords": [
      47.8093,
      2.3053
    ],
    "year": 971,
    "date_str": "971 [?]-1046",
    "description": "Visited: Eicfredu (Pul Oliva)"
  },
  {
    "step": 97,
    "type": "stop",
    "name": "par",
    "coords": null,
    "year": 971,
    "date_str": "971 [?]-1046",
    "description": "Visited: Quidquid (Callia Juagiu P de christiana)"
  },
  {
    "step": 98,
    "type": "stop",
    "name": "Limoges",
    "coords": null,
    "year": 971,
    "date_str": "971 [?]-1046",
    "description": "Visited: Quod (1 Gereslees)"
  },
  {
    "step": 99,
    "type": "stop",
    "name": "Nanteuil-en-Vall\u00e9e Abbey, France",
    "coords": [
      46.0022,
      0.2818
    ],
    "year": 971,
    "date_str": "971 [?]-1046",
    "description": "Visited: Ram (abb\u00e9 de S. 988)"
  },
  {
    "step": 100,
    "type": "stop",
    "name": "Fleury Abbey, France",
    "coords": [
      47.8093,
      2.3053
    ],
    "year": 971,
    "date_str": "971 [?]-1046",
    "description": "Visited: Que (Pul Oliva)"
  },
  {
    "step": 101,
    "type": "stop",
    "name": "par",
    "coords": null,
    "year": 971,
    "date_str": "971 [?]-1046",
    "description": "Visited: Succurrer (Callia Juagiu P de christiana)"
  },
  {
    "step": 102,
    "type": "stop",
    "name": "Limoges",
    "coords": null,
    "year": 971,
    "date_str": "971 [?]-1046",
    "description": "Visited: Ode (1 Gereslees)"
  },
  {
    "step": 103,
    "type": "stop",
    "name": "Nanteuil-en-Vall\u00e9e Abbey, France",
    "coords": [
      46.0022,
      0.2818
    ],
    "year": 971,
    "date_str": "971 [?]-1046",
    "description": "Visited: Cugal (abb\u00e9 de S. 988)"
  },
  {
    "step": 104,
    "type": "stop",
    "name": "Fleury Abbey, France",
    "coords": [
      47.8093,
      2.3053
    ],
    "year": 971,
    "date_str": "971 [?]-1046",
    "description": "Visited: Guifred (Pul Oliva)"
  },
  {
    "step": 105,
    "type": "stop",
    "name": "par",
    "coords": null,
    "year": 971,
    "date_str": "971 [?]-1046",
    "description": "Visited: Audegario (Callia Juagiu P de christiana)"
  },
  {
    "step": 106,
    "type": "stop",
    "name": "Limoges",
    "coords": null,
    "year": 971,
    "date_str": "971 [?]-1046",
    "description": "Visited: Jeticiam (1 Gereslees)"
  },
  {
    "step": 107,
    "type": "stop",
    "name": "Fleury Abbey, France",
    "coords": [
      47.8093,
      2.3053
    ],
    "year": 971,
    "date_str": "971 [?]-1046",
    "description": "Visited: Orgellitanensis (Pul Oliva)"
  },
  {
    "step": 108,
    "type": "stop",
    "name": "par",
    "coords": null,
    "year": 971,
    "date_str": "971 [?]-1046",
    "description": "Visited: Ut (Callia Juagiu P de christiana)"
  },
  {
    "step": 109,
    "type": "stop",
    "name": "Limoges",
    "coords": null,
    "year": 971,
    "date_str": "971 [?]-1046",
    "description": "Visited: Auxiliumque (1 Gereslees)"
  },
  {
    "step": 110,
    "type": "stop",
    "name": "Nanteuil-en-Vall\u00e9e Abbey, France",
    "coords": [
      46.0022,
      0.2818
    ],
    "year": 971,
    "date_str": "971 [?]-1046",
    "description": "Visited: Ansegiso (abb\u00e9 de S. 988)"
  },
  {
    "step": 111,
    "type": "stop",
    "name": "Fleury Abbey, France",
    "coords": [
      47.8093,
      2.3053
    ],
    "year": 971,
    "date_str": "971 [?]-1046",
    "description": "Visited: Ingenitu (Pul Oliva)"
  },
  {
    "step": 112,
    "type": "stop",
    "name": "par",
    "coords": null,
    "year": 971,
    "date_str": "971 [?]-1046",
    "description": "Visited: Christ (Callia Juagiu P de christiana)"
  },
  {
    "step": 113,
    "type": "stop",
    "name": "Limoges",
    "coords": null,
    "year": 971,
    "date_str": "971 [?]-1046",
    "description": "Visited: Hinc (1 Gereslees)"
  },
  {
    "step": 114,
    "type": "stop",
    "name": "Nanteuil-en-Vall\u00e9e Abbey, France",
    "coords": [
      46.0022,
      0.2818
    ],
    "year": 971,
    "date_str": "971 [?]-1046",
    "description": "Visited: Tum (abb\u00e9 de S. 988)"
  },
  {
    "step": 115,
    "type": "stop",
    "name": "Fleury Abbey, France",
    "coords": [
      47.8093,
      2.3053
    ],
    "year": 971,
    "date_str": "971 [?]-1046",
    "description": "Visited: Goscelinus (Pul Oliva)"
  },
  {
    "step": 116,
    "type": "stop",
    "name": "par",
    "coords": null,
    "year": 971,
    "date_str": "971 [?]-1046",
    "description": "Visited: Hersindis (Callia Juagiu P de christiana)"
  },
  {
    "step": 117,
    "type": "stop",
    "name": "Limoges",
    "coords": null,
    "year": 971,
    "date_str": "971 [?]-1046",
    "description": "Visited: Herbertus (1 Gereslees)"
  },
  {
    "step": 118,
    "type": "stop",
    "name": "Nanteuil-en-Vall\u00e9e Abbey, France",
    "coords": [
      46.0022,
      0.2818
    ],
    "year": 971,
    "date_str": "971 [?]-1046",
    "description": "Visited: Orl (abb\u00e9 de S. 988)"
  },
  {
    "step": 119,
    "type": "stop",
    "name": "Fleury Abbey, France",
    "coords": [
      47.8093,
      2.3053
    ],
    "year": 971,
    "date_str": "971 [?]-1046",
    "description": "Visited: Cursus (Pul Oliva)"
  },
  {
    "step": 120,
    "type": "stop",
    "name": "par",
    "coords": null,
    "year": 971,
    "date_str": "971 [?]-1046",
    "description": "Visited: Novimus (Callia Juagiu P de christiana)"
  },
  {
    "step": 121,
    "type": "stop",
    "name": "Limoges",
    "coords": null,
    "year": 971,
    "date_str": "971 [?]-1046",
    "description": "Visited: Fecimus (1 Gereslees)"
  },
  {
    "step": 122,
    "type": "stop",
    "name": "Nanteuil-en-Vall\u00e9e Abbey, France",
    "coords": [
      46.0022,
      0.2818
    ],
    "year": 971,
    "date_str": "971 [?]-1046",
    "description": "Visited: Jeg (abb\u00e9 de S. 988)"
  },
  {
    "step": 123,
    "type": "stop",
    "name": "Fleury Abbey, France",
    "coords": [
      47.8093,
      2.3053
    ],
    "year": 971,
    "date_str": "971 [?]-1046",
    "description": "Visited: Equa (Pul Oliva)"
  },
  {
    "step": 124,
    "type": "stop",
    "name": "par",
    "coords": null,
    "year": 971,
    "date_str": "971 [?]-1046",
    "description": "Visited: Ripak (Callia Juagiu P de christiana)"
  },
  {
    "step": 125,
    "type": "stop",
    "name": "Limoges",
    "coords": null,
    "year": 971,
    "date_str": "971 [?]-1046",
    "description": "Visited: Volfridus (1 Gereslees)"
  },
  {
    "step": 126,
    "type": "stop",
    "name": "Nanteuil-en-Vall\u00e9e Abbey, France",
    "coords": [
      46.0022,
      0.2818
    ],
    "year": 971,
    "date_str": "971 [?]-1046",
    "description": "Visited: Hereboldu (abb\u00e9 de S. 988)"
  },
  {
    "step": 127,
    "type": "stop",
    "name": "Fleury Abbey, France",
    "coords": [
      47.8093,
      2.3053
    ],
    "year": 971,
    "date_str": "971 [?]-1046",
    "description": "Visited: Cursus (Pul Oliva)"
  },
  {
    "step": 128,
    "type": "stop",
    "name": "par",
    "coords": null,
    "year": 971,
    "date_str": "971 [?]-1046",
    "description": "Visited: Novimus (Callia Juagiu P de christiana)"
  },
  {
    "step": 129,
    "type": "stop",
    "name": "Limoges",
    "coords": null,
    "year": 971,
    "date_str": "971 [?]-1046",
    "description": "Visited: Fecimus (1 Gereslees)"
  },
  {
    "step": 130,
    "type": "stop",
    "name": "Nanteuil-en-Vall\u00e9e Abbey, France",
    "coords": [
      46.0022,
      0.2818
    ],
    "year": 971,
    "date_str": "971 [?]-1046",
    "description": "Visited: Guncti (abb\u00e9 de S. 988)"
  },
  {
    "step": 131,
    "type": "stop",
    "name": "Fleury Abbey, France",
    "coords": [
      47.8093,
      2.3053
    ],
    "year": 971,
    "date_str": "971 [?]-1046",
    "description": "Visited: Equa (Pul Oliva)"
  },
  {
    "step": 132,
    "type": "stop",
    "name": "par",
    "coords": null,
    "year": 971,
    "date_str": "971 [?]-1046",
    "description": "Visited: Jozpertus (Callia Juagiu P de christiana)"
  },
  {
    "step": 133,
    "type": "stop",
    "name": "Limoges",
    "coords": null,
    "year": 971,
    "date_str": "971 [?]-1046",
    "description": "Visited: Biqa (1 Gereslees)"
  },
  {
    "step": 134,
    "type": "stop",
    "name": "Nanteuil-en-Vall\u00e9e Abbey, France",
    "coords": [
      46.0022,
      0.2818
    ],
    "year": 971,
    "date_str": "971 [?]-1046",
    "description": "Visited: Lanzelinus (abb\u00e9 de S. 988)"
  },
  {
    "step": 135,
    "type": "stop",
    "name": "Fleury Abbey, France",
    "coords": [
      47.8093,
      2.3053
    ],
    "year": 971,
    "date_str": "971 [?]-1046",
    "description": "Visited: Turone (Pul Oliva)"
  },
  {
    "step": 136,
    "type": "stop",
    "name": "par",
    "coords": null,
    "year": 971,
    "date_str": "971 [?]-1046",
    "description": "Visited: Sed (Callia Juagiu P de christiana)"
  },
  {
    "step": 137,
    "type": "stop",
    "name": "Limoges",
    "coords": null,
    "year": 971,
    "date_str": "971 [?]-1046",
    "description": "Visited: Hos (1 Gereslees)"
  },
  {
    "step": 138,
    "type": "stop",
    "name": "Nanteuil-en-Vall\u00e9e Abbey, France",
    "coords": [
      46.0022,
      0.2818
    ],
    "year": 971,
    "date_str": "971 [?]-1046",
    "description": "Visited: Nomina (abb\u00e9 de S. 988)"
  },
  {
    "step": 139,
    "type": "stop",
    "name": "Fleury Abbey, France",
    "coords": [
      47.8093,
      2.3053
    ],
    "year": 971,
    "date_str": "971 [?]-1046",
    "description": "Visited: Ermenardu (Pul Oliva)"
  },
  {
    "step": 140,
    "type": "stop",
    "name": "par",
    "coords": null,
    "year": 971,
    "date_str": "971 [?]-1046",
    "description": "Visited: Provasiu (Callia Juagiu P de christiana)"
  },
  {
    "step": 141,
    "type": "stop",
    "name": "Limoges",
    "coords": null,
    "year": 971,
    "date_str": "971 [?]-1046",
    "description": "Visited: Johanne (1 Gereslees)"
  },
  {
    "step": 142,
    "type": "stop",
    "name": "Nanteuil-en-Vall\u00e9e Abbey, France",
    "coords": [
      46.0022,
      0.2818
    ],
    "year": 971,
    "date_str": "971 [?]-1046",
    "description": "Visited: Griboldu (abb\u00e9 de S. 988)"
  },
  {
    "step": 143,
    "type": "stop",
    "name": "Fleury Abbey, France",
    "coords": [
      47.8093,
      2.3053
    ],
    "year": 971,
    "date_str": "971 [?]-1046",
    "description": "Visited: Warnerus (Pul Oliva)"
  },
  {
    "step": 144,
    "type": "stop",
    "name": "par",
    "coords": null,
    "year": 971,
    "date_str": "971 [?]-1046",
    "description": "Visited: Vuipertus (Callia Juagiu P de christiana)"
  },
  {
    "step": 145,
    "type": "stop",
    "name": "Limoges",
    "coords": null,
    "year": 971,
    "date_str": "971 [?]-1046",
    "description": "Visited: Herbertus (1 Gereslees)"
  },
  {
    "step": 146,
    "type": "stop",
    "name": "Nanteuil-en-Vall\u00e9e Abbey, France",
    "coords": [
      46.0022,
      0.2818
    ],
    "year": 971,
    "date_str": "971 [?]-1046",
    "description": "Visited: Fecimus (abb\u00e9 de S. 988)"
  },
  {
    "step": 147,
    "type": "stop",
    "name": "Fleury Abbey, France",
    "coords": [
      47.8093,
      2.3053
    ],
    "year": 971,
    "date_str": "971 [?]-1046",
    "description": "Visited: Pr (Pul Oliva)"
  },
  {
    "step": 148,
    "type": "stop",
    "name": "par",
    "coords": null,
    "year": 971,
    "date_str": "971 [?]-1046",
    "description": "Visited: Turoldu (Callia Juagiu P de christiana)"
  },
  {
    "step": 149,
    "type": "stop",
    "name": "Limoges",
    "coords": null,
    "year": 971,
    "date_str": "971 [?]-1046",
    "description": "Visited: Tiberiu (1 Gereslees)"
  },
  {
    "step": 150,
    "type": "stop",
    "name": "Nanteuil-en-Vall\u00e9e Abbey, France",
    "coords": [
      46.0022,
      0.2818
    ],
    "year": 971,
    "date_str": "971 [?]-1046",
    "description": "Visited: Hubertuss (abb\u00e9 de S. 988)"
  },
  {
    "step": 151,
    "type": "stop",
    "name": "Fleury Abbey, France",
    "coords": [
      47.8093,
      2.3053
    ],
    "year": 971,
    "date_str": "971 [?]-1046",
    "description": "Visited: Harduinus (Pul Oliva)"
  },
  {
    "step": 152,
    "type": "stop",
    "name": "par",
    "coords": null,
    "year": 971,
    "date_str": "971 [?]-1046",
    "description": "Visited: Dominum (Callia Juagiu P de christiana)"
  },
  {
    "step": 153,
    "type": "stop",
    "name": "Limoges",
    "coords": null,
    "year": 971,
    "date_str": "971 [?]-1046",
    "description": "Visited: Et (1 Gereslees)"
  },
  {
    "step": 154,
    "type": "stop",
    "name": "Nanteuil-en-Vall\u00e9e Abbey, France",
    "coords": [
      46.0022,
      0.2818
    ],
    "year": 971,
    "date_str": "971 [?]-1046",
    "description": "Visited: Et (abb\u00e9 de S. 988)"
  },
  {
    "step": 155,
    "type": "stop",
    "name": "Fleury Abbey, France",
    "coords": [
      47.8093,
      2.3053
    ],
    "year": 971,
    "date_str": "971 [?]-1046",
    "description": "Visited: Cessit (Pul Oliva)"
  },
  {
    "step": 156,
    "type": "stop",
    "name": "par",
    "coords": null,
    "year": 971,
    "date_str": "971 [?]-1046",
    "description": "Visited: Abdical (Callia Juagiu P de christiana)"
  },
  {
    "step": 157,
    "type": "stop",
    "name": "Limoges",
    "coords": null,
    "year": 971,
    "date_str": "971 [?]-1046",
    "description": "Visited: Copturus (1 Gereslees)"
  },
  {
    "step": 158,
    "type": "stop",
    "name": "Nanteuil-en-Vall\u00e9e Abbey, France",
    "coords": [
      46.0022,
      0.2818
    ],
    "year": 971,
    "date_str": "971 [?]-1046",
    "description": "Visited: Ansoldus (abb\u00e9 de S. 988)"
  },
  {
    "step": 159,
    "type": "stop",
    "name": "Fleury Abbey, France",
    "coords": [
      47.8093,
      2.3053
    ],
    "year": 971,
    "date_str": "971 [?]-1046",
    "description": "Visited: Ut (Pul Oliva)"
  },
  {
    "step": 160,
    "type": "stop",
    "name": "par",
    "coords": null,
    "year": 971,
    "date_str": "971 [?]-1046",
    "description": "Visited: Pace (Callia Juagiu P de christiana)"
  },
  {
    "step": 161,
    "type": "stop",
    "name": "Limoges",
    "coords": null,
    "year": 971,
    "date_str": "971 [?]-1046",
    "description": "Visited: Ame (1 Gereslees)"
  },
  {
    "step": 162,
    "type": "stop",
    "name": "Nanteuil-en-Vall\u00e9e Abbey, France",
    "coords": [
      46.0022,
      0.2818
    ],
    "year": 971,
    "date_str": "971 [?]-1046",
    "description": "Visited: Meau (abb\u00e9 de S. 988)"
  },
  {
    "step": 163,
    "type": "stop",
    "name": "Fleury Abbey, France",
    "coords": [
      47.8093,
      2.3053
    ],
    "year": 971,
    "date_str": "971 [?]-1046",
    "description": "Visited: Pectora (Pul Oliva)"
  },
  {
    "step": 164,
    "type": "stop",
    "name": "par",
    "coords": null,
    "year": 971,
    "date_str": "971 [?]-1046",
    "description": "Visited: Martini (Callia Juagiu P de christiana)"
  },
  {
    "step": 165,
    "type": "stop",
    "name": "Limoges",
    "coords": null,
    "year": 971,
    "date_str": "971 [?]-1046",
    "description": "Visited: Domini (1 Gereslees)"
  },
  {
    "step": 166,
    "type": "stop",
    "name": "Nanteuil-en-Vall\u00e9e Abbey, France",
    "coords": [
      46.0022,
      0.2818
    ],
    "year": 971,
    "date_str": "971 [?]-1046",
    "description": "Visited: Qui (abb\u00e9 de S. 988)"
  },
  {
    "step": 167,
    "type": "stop",
    "name": "Fleury Abbey, France",
    "coords": [
      47.8093,
      2.3053
    ],
    "year": 971,
    "date_str": "971 [?]-1046",
    "description": "Visited: Cr (Pul Oliva)"
  },
  {
    "step": 168,
    "type": "stop",
    "name": "par",
    "coords": null,
    "year": 971,
    "date_str": "971 [?]-1046",
    "description": "Visited: Ascelinu (Callia Juagiu P de christiana)"
  },
  {
    "step": 169,
    "type": "stop",
    "name": "Limoges",
    "coords": null,
    "year": 971,
    "date_str": "971 [?]-1046",
    "description": "Visited: Stephanus (1 Gereslees)"
  },
  {
    "step": 170,
    "type": "stop",
    "name": "Nanteuil-en-Vall\u00e9e Abbey, France",
    "coords": [
      46.0022,
      0.2818
    ],
    "year": 971,
    "date_str": "971 [?]-1046",
    "description": "Visited: Quod (abb\u00e9 de S. 988)"
  },
  {
    "step": 171,
    "type": "stop",
    "name": "Fleury Abbey, France",
    "coords": [
      47.8093,
      2.3053
    ],
    "year": 971,
    "date_str": "971 [?]-1046",
    "description": "Visited: Fratribus (Pul Oliva)"
  },
  {
    "step": 172,
    "type": "stop",
    "name": "par",
    "coords": null,
    "year": 971,
    "date_str": "971 [?]-1046",
    "description": "Visited: Exilium (Callia Juagiu P de christiana)"
  },
  {
    "step": 173,
    "type": "stop",
    "name": "Limoges",
    "coords": null,
    "year": 971,
    "date_str": "971 [?]-1046",
    "description": "Visited: Que (1 Gereslees)"
  },
  {
    "step": 174,
    "type": "stop",
    "name": "Nanteuil-en-Vall\u00e9e Abbey, France",
    "coords": [
      46.0022,
      0.2818
    ],
    "year": 971,
    "date_str": "971 [?]-1046",
    "description": "Visited: Tcodcrico (abb\u00e9 de S. 988)"
  },
  {
    "step": 175,
    "type": "stop",
    "name": "Fleury Abbey, France",
    "coords": [
      47.8093,
      2.3053
    ],
    "year": 971,
    "date_str": "971 [?]-1046",
    "description": "Visited: Desideriu (Pul Oliva)"
  },
  {
    "step": 176,
    "type": "stop",
    "name": "par",
    "coords": null,
    "year": 971,
    "date_str": "971 [?]-1046",
    "description": "Visited: Non (Callia Juagiu P de christiana)"
  },
  {
    "step": 177,
    "type": "stop",
    "name": "Limoges",
    "coords": null,
    "year": 971,
    "date_str": "971 [?]-1046",
    "description": "Visited: Jugendu (1 Gereslees)"
  },
  {
    "step": 178,
    "type": "stop",
    "name": "Nanteuil-en-Vall\u00e9e Abbey, France",
    "coords": [
      46.0022,
      0.2818
    ],
    "year": 971,
    "date_str": "971 [?]-1046",
    "description": "Visited: Hestreboldo (abb\u00e9 de S. 988)"
  },
  {
    "step": 179,
    "type": "stop",
    "name": "Fleury Abbey, France",
    "coords": [
      47.8093,
      2.3053
    ],
    "year": 971,
    "date_str": "971 [?]-1046",
    "description": "Visited: Mors (Pul Oliva)"
  },
  {
    "step": 180,
    "type": "stop",
    "name": "par",
    "coords": null,
    "year": 971,
    "date_str": "971 [?]-1046",
    "description": "Visited: Asteriu (Callia Juagiu P de christiana)"
  },
  {
    "step": 181,
    "type": "stop",
    "name": "Limoges",
    "coords": null,
    "year": 971,
    "date_str": "971 [?]-1046",
    "description": "Visited: Haec (1 Gereslees)"
  },
  {
    "step": 182,
    "type": "stop",
    "name": "Nanteuil-en-Vall\u00e9e Abbey, France",
    "coords": [
      46.0022,
      0.2818
    ],
    "year": 971,
    "date_str": "971 [?]-1046",
    "description": "Visited: Geraldu (abb\u00e9 de S. 988)"
  },
  {
    "step": 183,
    "type": "stop",
    "name": "Fleury Abbey, France",
    "coords": [
      47.8093,
      2.3053
    ],
    "year": 971,
    "date_str": "971 [?]-1046",
    "description": "Visited: Wilelmus (Pul Oliva)"
  },
  {
    "step": 184,
    "type": "stop",
    "name": "par",
    "coords": null,
    "year": 971,
    "date_str": "971 [?]-1046",
    "description": "Visited: Moribus (Callia Juagiu P de christiana)"
  },
  {
    "step": 185,
    "type": "stop",
    "name": "Limoges",
    "coords": null,
    "year": 971,
    "date_str": "971 [?]-1046",
    "description": "Visited: Martino (1 Gereslees)"
  },
  {
    "step": 186,
    "type": "stop",
    "name": "Nanteuil-en-Vall\u00e9e Abbey, France",
    "coords": [
      46.0022,
      0.2818
    ],
    "year": 971,
    "date_str": "971 [?]-1046",
    "description": "Visited: Helisii (abb\u00e9 de S. 988)"
  },
  {
    "step": 187,
    "type": "stop",
    "name": "Fleury Abbey, France",
    "coords": [
      47.8093,
      2.3053
    ],
    "year": 971,
    "date_str": "971 [?]-1046",
    "description": "Visited: Nimirum (Pul Oliva)"
  },
  {
    "step": 188,
    "type": "stop",
    "name": "par",
    "coords": null,
    "year": 971,
    "date_str": "971 [?]-1046",
    "description": "Visited: Constantiu (Callia Juagiu P de christiana)"
  },
  {
    "step": 189,
    "type": "stop",
    "name": "Limoges",
    "coords": null,
    "year": 971,
    "date_str": "971 [?]-1046",
    "description": "Visited: Goastansa (1 Gereslees)"
  },
  {
    "step": 190,
    "type": "stop",
    "name": "Nanteuil-en-Vall\u00e9e Abbey, France",
    "coords": [
      46.0022,
      0.2818
    ],
    "year": 971,
    "date_str": "971 [?]-1046",
    "description": "Visited: Ititru (abb\u00e9 de S. 988)"
  },
  {
    "step": 191,
    "type": "stop",
    "name": "Fleury Abbey, France",
    "coords": [
      47.8093,
      2.3053
    ],
    "year": 971,
    "date_str": "971 [?]-1046",
    "description": "Visited: Domino (Pul Oliva)"
  },
  {
    "step": 192,
    "type": "stop",
    "name": "par",
    "coords": null,
    "year": 971,
    "date_str": "971 [?]-1046",
    "description": "Visited: Bernardus (Callia Juagiu P de christiana)"
  },
  {
    "step": 193,
    "type": "stop",
    "name": "Limoges",
    "coords": null,
    "year": 971,
    "date_str": "971 [?]-1046",
    "description": "Visited: Lagn (1 Gereslees)"
  },
  {
    "step": 194,
    "type": "stop",
    "name": "Nanteuil-en-Vall\u00e9e Abbey, France",
    "coords": [
      46.0022,
      0.2818
    ],
    "year": 971,
    "date_str": "971 [?]-1046",
    "description": "Visited: Et (abb\u00e9 de S. 988)"
  },
  {
    "step": 195,
    "type": "stop",
    "name": "Fleury Abbey, France",
    "coords": [
      47.8093,
      2.3053
    ],
    "year": 971,
    "date_str": "971 [?]-1046",
    "description": "Visited: Finibus (Pul Oliva)"
  },
  {
    "step": 196,
    "type": "stop",
    "name": "par",
    "coords": null,
    "year": 971,
    "date_str": "971 [?]-1046",
    "description": "Visited: Quod (Callia Juagiu P de christiana)"
  },
  {
    "step": 197,
    "type": "stop",
    "name": "Limoges",
    "coords": null,
    "year": 971,
    "date_str": "971 [?]-1046",
    "description": "Visited: Benedict (1 Gereslees)"
  },
  {
    "step": 198,
    "type": "stop",
    "name": "Nanteuil-en-Vall\u00e9e Abbey, France",
    "coords": [
      46.0022,
      0.2818
    ],
    "year": 971,
    "date_str": "971 [?]-1046",
    "description": "Visited: Sur (abb\u00e9 de S. 988)"
  },
  {
    "step": 199,
    "type": "stop",
    "name": "Fleury Abbey, France",
    "coords": [
      47.8093,
      2.3053
    ],
    "year": 971,
    "date_str": "971 [?]-1046",
    "description": "Visited: Servatii (Pul Oliva)"
  },
  {
    "step": 200,
    "type": "stop",
    "name": "par",
    "coords": null,
    "year": 971,
    "date_str": "971 [?]-1046",
    "description": "Visited: Sicaput (Callia Juagiu P de christiana)"
  },
  {
    "step": 201,
    "type": "stop",
    "name": "Limoges",
    "coords": null,
    "year": 971,
    "date_str": "971 [?]-1046",
    "description": "Visited: Quod (1 Gereslees)"
  },
  {
    "step": 202,
    "type": "stop",
    "name": "Nanteuil-en-Vall\u00e9e Abbey, France",
    "coords": [
      46.0022,
      0.2818
    ],
    "year": 971,
    "date_str": "971 [?]-1046",
    "description": "Visited: Foederibus (abb\u00e9 de S. 988)"
  },
  {
    "step": 203,
    "type": "stop",
    "name": "Fleury Abbey, France",
    "coords": [
      47.8093,
      2.3053
    ],
    "year": 971,
    "date_str": "971 [?]-1046",
    "description": "Visited: Visere (Pul Oliva)"
  },
  {
    "step": 204,
    "type": "stop",
    "name": "par",
    "coords": null,
    "year": 971,
    "date_str": "971 [?]-1046",
    "description": "Visited: Pro (Callia Juagiu P de christiana)"
  },
  {
    "step": 205,
    "type": "stop",
    "name": "Limoges",
    "coords": null,
    "year": 971,
    "date_str": "971 [?]-1046",
    "description": "Visited: Sit (1 Gereslees)"
  },
  {
    "step": 206,
    "type": "stop",
    "name": "Nanteuil-en-Vall\u00e9e Abbey, France",
    "coords": [
      46.0022,
      0.2818
    ],
    "year": 971,
    "date_str": "971 [?]-1046",
    "description": "Visited: Et (abb\u00e9 de S. 988)"
  },
  {
    "step": 207,
    "type": "stop",
    "name": "Fleury Abbey, France",
    "coords": [
      47.8093,
      2.3053
    ],
    "year": 971,
    "date_str": "971 [?]-1046",
    "description": "Visited: Valet (Pul Oliva)"
  },
  {
    "step": 208,
    "type": "stop",
    "name": "par",
    "coords": null,
    "year": 971,
    "date_str": "971 [?]-1046",
    "description": "Visited: Mors (Callia Juagiu P de christiana)"
  },
  {
    "step": 209,
    "type": "stop",
    "name": "Limoges",
    "coords": null,
    "year": 971,
    "date_str": "971 [?]-1046",
    "description": "Visited: Perderet (1 Gereslees)"
  },
  {
    "step": 210,
    "type": "stop",
    "name": "Fleury Abbey, France",
    "coords": [
      47.8093,
      2.3053
    ],
    "year": 971,
    "date_str": "971 [?]-1046",
    "description": "Visited: Nobis (Pul Oliva)"
  },
  {
    "step": 211,
    "type": "stop",
    "name": "par",
    "coords": null,
    "year": 971,
    "date_str": "971 [?]-1046",
    "description": "Visited: Congaudete (Callia Juagiu P de christiana)"
  },
  {
    "step": 212,
    "type": "stop",
    "name": "Limoges",
    "coords": null,
    "year": 971,
    "date_str": "971 [?]-1046",
    "description": "Visited: Vita (1 Gereslees)"
  },
  {
    "step": 213,
    "type": "stop",
    "name": "Nanteuil-en-Vall\u00e9e Abbey, France",
    "coords": [
      46.0022,
      0.2818
    ],
    "year": 971,
    "date_str": "971 [?]-1046",
    "description": "Visited: Trajectum (abb\u00e9 de S. 988)"
  },
  {
    "step": 214,
    "type": "stop",
    "name": "Fleury Abbey, France",
    "coords": [
      47.8093,
      2.3053
    ],
    "year": 971,
    "date_str": "971 [?]-1046",
    "description": "Visited: Turbarique (Pul Oliva)"
  },
  {
    "step": 215,
    "type": "stop",
    "name": "par",
    "coords": null,
    "year": 971,
    "date_str": "971 [?]-1046",
    "description": "Visited: Elegi (Callia Juagiu P de christiana)"
  },
  {
    "step": 216,
    "type": "stop",
    "name": "Limoges",
    "coords": null,
    "year": 971,
    "date_str": "971 [?]-1046",
    "description": "Visited: Subtraxit (1 Gereslees)"
  },
  {
    "step": 217,
    "type": "stop",
    "name": "Nanteuil-en-Vall\u00e9e Abbey, France",
    "coords": [
      46.0022,
      0.2818
    ],
    "year": 971,
    "date_str": "971 [?]-1046",
    "description": "Visited: Lu (abb\u00e9 de S. 988)"
  },
  {
    "step": 218,
    "type": "stop",
    "name": "Fleury Abbey, France",
    "coords": [
      47.8093,
      2.3053
    ],
    "year": 971,
    "date_str": "971 [?]-1046",
    "description": "Visited: Letificat (Pul Oliva)"
  },
  {
    "step": 219,
    "type": "stop",
    "name": "par",
    "coords": null,
    "year": 971,
    "date_str": "971 [?]-1046",
    "description": "Visited: Non (Callia Juagiu P de christiana)"
  },
  {
    "step": 220,
    "type": "stop",
    "name": "Limoges",
    "coords": null,
    "year": 971,
    "date_str": "971 [?]-1046",
    "description": "Visited: Nam (1 Gereslees)"
  },
  {
    "step": 221,
    "type": "stop",
    "name": "Fleury Abbey, France",
    "coords": [
      47.8093,
      2.3053
    ],
    "year": 971,
    "date_str": "971 [?]-1046",
    "description": "Visited: Aquens (Pul Oliva)"
  },
  {
    "step": 222,
    "type": "stop",
    "name": "par",
    "coords": null,
    "year": 971,
    "date_str": "971 [?]-1046",
    "description": "Visited: Martynus (Callia Juagiu P de christiana)"
  },
  {
    "step": 223,
    "type": "stop",
    "name": "Limoges",
    "coords": null,
    "year": 971,
    "date_str": "971 [?]-1046",
    "description": "Visited: Albertu (1 Gereslees)"
  },
  {
    "step": 224,
    "type": "stop",
    "name": "Nanteuil-en-Vall\u00e9e Abbey, France",
    "coords": [
      46.0022,
      0.2818
    ],
    "year": 971,
    "date_str": "971 [?]-1046",
    "description": "Visited: Jam (abb\u00e9 de S. 988)"
  },
  {
    "step": 225,
    "type": "stop",
    "name": "Fleury Abbey, France",
    "coords": [
      47.8093,
      2.3053
    ],
    "year": 971,
    "date_str": "971 [?]-1046",
    "description": "Visited: Martham (Pul Oliva)"
  },
  {
    "step": 226,
    "type": "stop",
    "name": "par",
    "coords": null,
    "year": 971,
    "date_str": "971 [?]-1046",
    "description": "Visited: Mutavit (Callia Juagiu P de christiana)"
  },
  {
    "step": 227,
    "type": "stop",
    "name": "Limoges",
    "coords": null,
    "year": 971,
    "date_str": "971 [?]-1046",
    "description": "Visited: Alter (1 Gereslees)"
  },
  {
    "step": 228,
    "type": "stop",
    "name": "Nanteuil-en-Vall\u00e9e Abbey, France",
    "coords": [
      46.0022,
      0.2818
    ],
    "year": 971,
    "date_str": "971 [?]-1046",
    "description": "Visited: Dulces (abb\u00e9 de S. 988)"
  },
  {
    "step": 229,
    "type": "stop",
    "name": "Fleury Abbey, France",
    "coords": [
      47.8093,
      2.3053
    ],
    "year": 971,
    "date_str": "971 [?]-1046",
    "description": "Visited: Luget (Pul Oliva)"
  },
  {
    "step": 230,
    "type": "stop",
    "name": "par",
    "coords": null,
    "year": 971,
    "date_str": "971 [?]-1046",
    "description": "Visited: Occasu (Callia Juagiu P de christiana)"
  },
  {
    "step": 231,
    "type": "stop",
    "name": "Limoges",
    "coords": null,
    "year": 971,
    "date_str": "971 [?]-1046",
    "description": "Visited: Ordine (1 Gereslees)"
  },
  {
    "step": 232,
    "type": "stop",
    "name": "Fleury Abbey, France",
    "coords": [
      47.8093,
      2.3053
    ],
    "year": 971,
    "date_str": "971 [?]-1046",
    "description": "Visited: Quos (Pul Oliva)"
  },
  {
    "step": 233,
    "type": "stop",
    "name": "par",
    "coords": null,
    "year": 971,
    "date_str": "971 [?]-1046",
    "description": "Visited: Berengerins (Callia Juagiu P de christiana)"
  },
  {
    "step": 234,
    "type": "stop",
    "name": "Limoges",
    "coords": null,
    "year": 971,
    "date_str": "971 [?]-1046",
    "description": "Visited: Alecherius (1 Gereslees)"
  },
  {
    "step": 235,
    "type": "stop",
    "name": "Nanteuil-en-Vall\u00e9e Abbey, France",
    "coords": [
      46.0022,
      0.2818
    ],
    "year": 971,
    "date_str": "971 [?]-1046",
    "description": "Visited: Stephanus (abb\u00e9 de S. 988)"
  },
  {
    "step": 236,
    "type": "stop",
    "name": "Brioude Abbey, France",
    "coords": [
      45.2933,
      3.3847
    ],
    "year": 971,
    "date_str": "971 [?]-1046",
    "description": "Visited: Prvpos (' cit\u00e9 pour Je milieu du XI s restitution)"
  },
  {
    "step": 237,
    "type": "stop",
    "name": "Fleury Abbey, France",
    "coords": [
      47.8093,
      2.3053
    ],
    "year": 971,
    "date_str": "971 [?]-1046",
    "description": "Visited: Dyonisii (Pul Oliva)"
  },
  {
    "step": 238,
    "type": "stop",
    "name": "par",
    "coords": null,
    "year": 971,
    "date_str": "971 [?]-1046",
    "description": "Visited: Marti (Callia Juagiu P de christiana)"
  },
  {
    "step": 239,
    "type": "stop",
    "name": "Limoges",
    "coords": null,
    "year": 971,
    "date_str": "971 [?]-1046",
    "description": "Visited: Fhoebus (1 Gereslees)"
  },
  {
    "step": 240,
    "type": "stop",
    "name": "Nanteuil-en-Vall\u00e9e Abbey, France",
    "coords": [
      46.0022,
      0.2818
    ],
    "year": 971,
    "date_str": "971 [?]-1046",
    "description": "Visited: Stephanus (abb\u00e9 de S. 988)"
  },
  {
    "step": 241,
    "type": "stop",
    "name": "Fleury Abbey, France",
    "coords": [
      47.8093,
      2.3053
    ],
    "year": 971,
    "date_str": "971 [?]-1046",
    "description": "Visited: Deu (Pul Oliva)"
  },
  {
    "step": 242,
    "type": "stop",
    "name": "par",
    "coords": null,
    "year": 971,
    "date_str": "971 [?]-1046",
    "description": "Visited: Et (Callia Juagiu P de christiana)"
  },
  {
    "step": 243,
    "type": "stop",
    "name": "Limoges",
    "coords": null,
    "year": 971,
    "date_str": "971 [?]-1046",
    "description": "Visited: Quis (1 Gereslees)"
  },
  {
    "step": 244,
    "type": "stop",
    "name": "Fleury Abbey, France",
    "coords": [
      47.8093,
      2.3053
    ],
    "year": 971,
    "date_str": "971 [?]-1046",
    "description": "Visited: Que (Pul Oliva)"
  },
  {
    "step": 245,
    "type": "stop",
    "name": "par",
    "coords": null,
    "year": 971,
    "date_str": "971 [?]-1046",
    "description": "Visited: Participant (Callia Juagiu P de christiana)"
  },
  {
    "step": 246,
    "type": "stop",
    "name": "Limoges",
    "coords": null,
    "year": 971,
    "date_str": "971 [?]-1046",
    "description": "Visited: Sunt (1 Gereslees)"
  },
  {
    "step": 247,
    "type": "stop",
    "name": "Fleury Abbey, France",
    "coords": [
      47.8093,
      2.3053
    ],
    "year": 971,
    "date_str": "971 [?]-1046",
    "description": "Visited: Non (Pul Oliva)"
  },
  {
    "step": 248,
    "type": "stop",
    "name": "par",
    "coords": null,
    "year": 971,
    "date_str": "971 [?]-1046",
    "description": "Visited: Wifredi (Callia Juagiu P de christiana)"
  },
  {
    "step": 249,
    "type": "stop",
    "name": "Limoges",
    "coords": null,
    "year": 971,
    "date_str": "971 [?]-1046",
    "description": "Visited: Christo (1 Gereslees)"
  },
  {
    "step": 250,
    "type": "stop",
    "name": "Nanteuil-en-Vall\u00e9e Abbey, France",
    "coords": [
      46.0022,
      0.2818
    ],
    "year": 971,
    "date_str": "971 [?]-1046",
    "description": "Visited: Ite (abb\u00e9 de S. 988)"
  },
  {
    "step": 251,
    "type": "stop",
    "name": "Fleury Abbey, France",
    "coords": [
      47.8093,
      2.3053
    ],
    "year": 971,
    "date_str": "971 [?]-1046",
    "description": "Visited: Olim (Pul Oliva)"
  },
  {
    "step": 252,
    "type": "stop",
    "name": "par",
    "coords": null,
    "year": 971,
    "date_str": "971 [?]-1046",
    "description": "Visited: Nostra (Callia Juagiu P de christiana)"
  },
  {
    "step": 253,
    "type": "stop",
    "name": "Limoges",
    "coords": null,
    "year": 971,
    "date_str": "971 [?]-1046",
    "description": "Visited: Nostro (1 Gereslees)"
  },
  {
    "step": 254,
    "type": "stop",
    "name": "Fleury Abbey, France",
    "coords": [
      47.8093,
      2.3053
    ],
    "year": 971,
    "date_str": "971 [?]-1046",
    "description": "Visited: Et (Pul Oliva)"
  },
  {
    "step": 255,
    "type": "stop",
    "name": "par",
    "coords": null,
    "year": 971,
    "date_str": "971 [?]-1046",
    "description": "Visited: Addictam (Callia Juagiu P de christiana)"
  },
  {
    "step": 256,
    "type": "stop",
    "name": "Limoges",
    "coords": null,
    "year": 971,
    "date_str": "971 [?]-1046",
    "description": "Visited: Ut (1 Gereslees)"
  },
  {
    "step": 257,
    "type": "stop",
    "name": "Nanteuil-en-Vall\u00e9e Abbey, France",
    "coords": [
      46.0022,
      0.2818
    ],
    "year": 971,
    "date_str": "971 [?]-1046",
    "description": "Visited: Coelitus (abb\u00e9 de S. 988)"
  },
  {
    "step": 258,
    "type": "stop",
    "name": "Fleury Abbey, France",
    "coords": [
      47.8093,
      2.3053
    ],
    "year": 971,
    "date_str": "971 [?]-1046",
    "description": "Visited: Hic (Pul Oliva)"
  },
  {
    "step": 259,
    "type": "stop",
    "name": "par",
    "coords": null,
    "year": 971,
    "date_str": "971 [?]-1046",
    "description": "Visited: Lethes (Callia Juagiu P de christiana)"
  },
  {
    "step": 260,
    "type": "stop",
    "name": "Limoges",
    "coords": null,
    "year": 971,
    "date_str": "971 [?]-1046",
    "description": "Visited: Baldrico (1 Gereslees)"
  },
  {
    "step": 261,
    "type": "stop",
    "name": "Nanteuil-en-Vall\u00e9e Abbey, France",
    "coords": [
      46.0022,
      0.2818
    ],
    "year": 971,
    "date_str": "971 [?]-1046",
    "description": "Visited: Lyo (abb\u00e9 de S. 988)"
  },
  {
    "step": 262,
    "type": "stop",
    "name": "Fleury Abbey, France",
    "coords": [
      47.8093,
      2.3053
    ],
    "year": 971,
    "date_str": "971 [?]-1046",
    "description": "Visited: Domino (Pul Oliva)"
  },
  {
    "step": 263,
    "type": "stop",
    "name": "par",
    "coords": null,
    "year": 971,
    "date_str": "971 [?]-1046",
    "description": "Visited: Conditor (Callia Juagiu P de christiana)"
  },
  {
    "step": 264,
    "type": "stop",
    "name": "Limoges",
    "coords": null,
    "year": 971,
    "date_str": "971 [?]-1046",
    "description": "Visited: Cunctaque (1 Gereslees)"
  },
  {
    "step": 265,
    "type": "stop",
    "name": "Nanteuil-en-Vall\u00e9e Abbey, France",
    "coords": [
      46.0022,
      0.2818
    ],
    "year": 971,
    "date_str": "971 [?]-1046",
    "description": "Visited: Cerritaniensis (abb\u00e9 de S. 988)"
  },
  {
    "step": 266,
    "type": "stop",
    "name": "Fleury Abbey, France",
    "coords": [
      47.8093,
      2.3053
    ],
    "year": 971,
    "date_str": "971 [?]-1046",
    "description": "Visited: Dis (Pul Oliva)"
  },
  {
    "step": 267,
    "type": "stop",
    "name": "par",
    "coords": null,
    "year": 971,
    "date_str": "971 [?]-1046",
    "description": "Visited: Quam (Callia Juagiu P de christiana)"
  },
  {
    "step": 268,
    "type": "stop",
    "name": "Limoges",
    "coords": null,
    "year": 971,
    "date_str": "971 [?]-1046",
    "description": "Visited: Wifred (1 Gereslees)"
  },
  {
    "step": 269,
    "type": "stop",
    "name": "Nanteuil-en-Vall\u00e9e Abbey, France",
    "coords": [
      46.0022,
      0.2818
    ],
    "year": 971,
    "date_str": "971 [?]-1046",
    "description": "Visited: Or (abb\u00e9 de S. 988)"
  },
  {
    "step": 270,
    "type": "stop",
    "name": "Fleury Abbey, France",
    "coords": [
      47.8093,
      2.3053
    ],
    "year": 971,
    "date_str": "971 [?]-1046",
    "description": "Visited: Item (Pul Oliva)"
  },
  {
    "step": 271,
    "type": "stop",
    "name": "par",
    "coords": null,
    "year": 971,
    "date_str": "971 [?]-1046",
    "description": "Visited: Croi (Callia Juagiu P de christiana)"
  },
  {
    "step": 272,
    "type": "stop",
    "name": "Limoges",
    "coords": null,
    "year": 971,
    "date_str": "971 [?]-1046",
    "description": "Visited: Item (1 Gereslees)"
  },
  {
    "step": 273,
    "type": "stop",
    "name": "Nanteuil-en-Vall\u00e9e Abbey, France",
    "coords": [
      46.0022,
      0.2818
    ],
    "year": 971,
    "date_str": "971 [?]-1046",
    "description": "Visited: Haec (abb\u00e9 de S. 988)"
  },
  {
    "step": 274,
    "type": "stop",
    "name": "par",
    "coords": null,
    "year": 1016,
    "date_str": "1016, novembre 1047, juin",
    "description": "Visited: Wifred (Callia Juagiu P de christiana)"
  },
  {
    "step": 275,
    "type": "stop",
    "name": "Limoges",
    "coords": null,
    "year": 1016,
    "date_str": "1016, novembre 1047, juin",
    "description": "Visited: Vosqu (1 Gereslees)"
  },
  {
    "step": 276,
    "type": "stop",
    "name": "Nanteuil-en-Vall\u00e9e Abbey, France",
    "coords": [
      46.0022,
      0.2818
    ],
    "year": 1016,
    "date_str": "1016, novembre 1047, juin",
    "description": "Visited: Si (abb\u00e9 de S. 988)"
  },
  {
    "step": 277,
    "type": "stop",
    "name": "Fleury Abbey, France",
    "coords": [
      47.8093,
      2.3053
    ],
    "year": 971,
    "date_str": "971 [?]-1046",
    "description": "Visited: Mammona (Pul Oliva)"
  },
  {
    "step": 278,
    "type": "stop",
    "name": "par",
    "coords": null,
    "year": 971,
    "date_str": "971 [?]-1046",
    "description": "Visited: Mortuus (Callia Juagiu P de christiana)"
  },
  {
    "step": 279,
    "type": "stop",
    "name": "Limoges",
    "coords": null,
    "year": 971,
    "date_str": "971 [?]-1046",
    "description": "Visited: Christ (1 Gereslees)"
  },
  {
    "step": 280,
    "type": "stop",
    "name": "Nanteuil-en-Vall\u00e9e Abbey, France",
    "coords": [
      46.0022,
      0.2818
    ],
    "year": 971,
    "date_str": "971 [?]-1046",
    "description": "Visited: Publica (abb\u00e9 de S. 988)"
  },
  {
    "step": 281,
    "type": "stop",
    "name": "Fleury Abbey, France",
    "coords": [
      47.8093,
      2.3053
    ],
    "year": 971,
    "date_str": "971 [?]-1046",
    "description": "Visited: Vobiscum (Pul Oliva)"
  },
  {
    "step": 282,
    "type": "stop",
    "name": "par",
    "coords": null,
    "year": 971,
    "date_str": "971 [?]-1046",
    "description": "Visited: Lux (Callia Juagiu P de christiana)"
  },
  {
    "step": 283,
    "type": "stop",
    "name": "Limoges",
    "coords": null,
    "year": 971,
    "date_str": "971 [?]-1046",
    "description": "Visited: Vit (1 Gereslees)"
  },
  {
    "step": 284,
    "type": "stop",
    "name": "Nanteuil-en-Vall\u00e9e Abbey, France",
    "coords": [
      46.0022,
      0.2818
    ],
    "year": 971,
    "date_str": "971 [?]-1046",
    "description": "Visited: Ame (abb\u00e9 de S. 988)"
  },
  {
    "step": 285,
    "type": "stop",
    "name": "Fleury Abbey, France",
    "coords": [
      47.8093,
      2.3053
    ],
    "year": 971,
    "date_str": "971 [?]-1046",
    "description": "Visited: Otia (Pul Oliva)"
  },
  {
    "step": 286,
    "type": "stop",
    "name": "par",
    "coords": null,
    "year": 971,
    "date_str": "971 [?]-1046",
    "description": "Visited: Domin (Callia Juagiu P de christiana)"
  },
  {
    "step": 287,
    "type": "stop",
    "name": "Limoges",
    "coords": null,
    "year": 971,
    "date_str": "971 [?]-1046",
    "description": "Visited: Itc (1 Gereslees)"
  },
  {
    "step": 288,
    "type": "stop",
    "name": "Nanteuil-en-Vall\u00e9e Abbey, France",
    "coords": [
      46.0022,
      0.2818
    ],
    "year": 971,
    "date_str": "971 [?]-1046",
    "description": "Visited: Propr (abb\u00e9 de S. 988)"
  },
  {
    "step": 289,
    "type": "stop",
    "name": "par",
    "coords": null,
    "year": 1016,
    "date_str": "1016, novembre 1047, juin",
    "description": "Visited: Mauro (Callia Juagiu P de christiana)"
  },
  {
    "step": 290,
    "type": "stop",
    "name": "Limoges",
    "coords": null,
    "year": 1016,
    "date_str": "1016, novembre 1047, juin",
    "description": "Visited: Walon (1 Gereslees)"
  },
  {
    "step": 291,
    "type": "stop",
    "name": "Nanteuil-en-Vall\u00e9e Abbey, France",
    "coords": [
      46.0022,
      0.2818
    ],
    "year": 1016,
    "date_str": "1016, novembre 1047, juin",
    "description": "Visited: Precipu (abb\u00e9 de S. 988)"
  },
  {
    "step": 292,
    "type": "stop",
    "name": "Fleury Abbey, France",
    "coords": [
      47.8093,
      2.3053
    ],
    "year": 971,
    "date_str": "971 [?]-1046",
    "description": "Visited: Guifredu (Pul Oliva)"
  },
  {
    "step": 293,
    "type": "stop",
    "name": "par",
    "coords": null,
    "year": 971,
    "date_str": "971 [?]-1046",
    "description": "Visited: Nos (Callia Juagiu P de christiana)"
  },
  {
    "step": 294,
    "type": "stop",
    "name": "Limoges",
    "coords": null,
    "year": 971,
    "date_str": "971 [?]-1046",
    "description": "Visited: Deo (1 Gereslees)"
  },
  {
    "step": 295,
    "type": "stop",
    "name": "Nanteuil-en-Vall\u00e9e Abbey, France",
    "coords": [
      46.0022,
      0.2818
    ],
    "year": 971,
    "date_str": "971 [?]-1046",
    "description": "Visited: Inecea (abb\u00e9 de S. 988)"
  },
  {
    "step": 296,
    "type": "stop",
    "name": "Fleury Abbey, France",
    "coords": [
      47.8093,
      2.3053
    ],
    "year": 971,
    "date_str": "971 [?]-1046",
    "description": "Visited: Geraldus (Pul Oliva)"
  },
  {
    "step": 297,
    "type": "stop",
    "name": "Limoges",
    "coords": null,
    "year": 971,
    "date_str": "971 [?]-1046",
    "description": "Visited: Jimina (1 Gereslees)"
  },
  {
    "step": 298,
    "type": "stop",
    "name": "Nanteuil-en-Vall\u00e9e Abbey, France",
    "coords": [
      46.0022,
      0.2818
    ],
    "year": 971,
    "date_str": "971 [?]-1046",
    "description": "Visited: Gairaldo (abb\u00e9 de S. 988)"
  },
  {
    "step": 299,
    "type": "stop",
    "name": "Brioude Abbey, France",
    "coords": [
      45.2933,
      3.3847
    ],
    "year": 971,
    "date_str": "971 [?]-1046",
    "description": "Visited: Virgineis (' cit\u00e9 pour Je milieu du XI s restitution)"
  },
  {
    "step": 300,
    "type": "stop",
    "name": "Saint-Denis Abbey, France",
    "coords": [
      48.9358,
      2.3598
    ],
    "year": 971,
    "date_str": "971 [?]-1046",
    "description": "Visited: Grandil ([\")"
  }
]